[
  {
    "home": "سلوجا دوبوج",
    "homeLogo": "https://jdwel.com/image/teams/724.png",
    "away": "فيليز",
    "awayLogo": "https://jdwel.com/image/teams/855.png",
    "score": "2 - 1",
    "time": "7:00 م"
  },
  {
    "home": "شيروكي برييغ",
    "homeLogo": "https://jdwel.com/image/teams/856.png",
    "away": "بوسيسيه",
    "awayLogo": "https://jdwel.com/image/teams/725.png",
    "score": "1 - 1",
    "time": "10:00 م"
  },
  {
    "home": "بوراتس بانيا لوكا",
    "homeLogo": "https://jdwel.com/image/teams/766.png",
    "away": "رودار برييدور",
    "awayLogo": "https://jdwel.com/image/teams/3448.png",
    "score": "6 - 0",
    "time": "10:00 م"
  },
  {
    "home": "جيلييزنيتشار ساراييفو",
    "homeLogo": "https://jdwel.com/image/teams/851.png",
    "away": "رادنيك بيلينا",
    "awayLogo": "https://jdwel.com/image/teams/857.png",
    "score": "1 - 1",
    "time": "10:00 م"
  },
  {
    "home": "رودار برييدور",
    "homeLogo": "https://jdwel.com/image/teams/3448.png",
    "away": "شيروكي برييغ",
    "awayLogo": "https://jdwel.com/image/teams/856.png",
    "score": "1 - 3",
    "time": "6:00 م"
  },
  {
    "home": "FK ساراييفو",
    "homeLogo": "https://jdwel.com/image/teams/858.png",
    "away": "رادنيك بيلينا",
    "awayLogo": "https://jdwel.com/image/teams/857.png",
    "score": "4 - 4",
    "time": "7:45 م"
  },
  {
    "home": "فيليز",
    "homeLogo": "https://jdwel.com/image/teams/855.png",
    "away": "بوراتس بانيا لوكا",
    "awayLogo": "https://jdwel.com/image/teams/766.png",
    "score": "1 - 1",
    "time": "10:00 م"
  },
  {
    "home": "بوسيسيه",
    "homeLogo": "https://jdwel.com/image/teams/725.png",
    "away": "جيلييزنيتشار ساراييفو",
    "awayLogo": "https://jdwel.com/image/teams/851.png",
    "score": "0 - 1",
    "time": "10:00 م"
  },
  {
    "home": "سلوجا دوبوج",
    "homeLogo": "https://jdwel.com/image/teams/724.png",
    "away": "FK ساراييفو",
    "awayLogo": "https://jdwel.com/image/teams/858.png",
    "score": "2 - 1",
    "time": "6:00 م"
  },
  {
    "home": "جيلييزنيتشار ساراييفو",
    "homeLogo": "https://jdwel.com/image/teams/851.png",
    "away": "رودار برييدور",
    "awayLogo": "https://jdwel.com/image/teams/3448.png",
    "score": "1 - 1",
    "time": "10:00 م"
  },
  {
    "home": "رادنيك بيلينا",
    "homeLogo": "https://jdwel.com/image/teams/857.png",
    "away": "بوسيسيه",
    "awayLogo": "https://jdwel.com/image/teams/725.png",
    "score": "2 - 0",
    "time": "7:45 م"
  },
  {
    "home": "شيروكي برييغ",
    "homeLogo": "https://jdwel.com/image/teams/856.png",
    "away": "فيليز",
    "awayLogo": "https://jdwel.com/image/teams/855.png",
    "score": "1 - 3",
    "time": "10:00 م"
  },
  {
    "home": "رودار برييدور",
    "homeLogo": "https://jdwel.com/image/teams/3448.png",
    "away": "رادنيك بيلينا",
    "awayLogo": "https://jdwel.com/image/teams/857.png",
    "score": "1 - 0",
    "time": "10:00 م"
  },
  {
    "home": "فيليز",
    "homeLogo": "https://jdwel.com/image/teams/855.png",
    "away": "جيلييزنيتشار ساراييفو",
    "awayLogo": "https://jdwel.com/image/teams/851.png",
    "score": "0 - 1",
    "time": "10:00 م"
  },
  {
    "home": "FK ساراييفو",
    "homeLogo": "https://jdwel.com/image/teams/858.png",
    "away": "بوسيسيه",
    "awayLogo": "https://jdwel.com/image/teams/725.png",
    "score": "2 - 1",
    "time": "10:00 م"
  },
  {
    "home": "سلوجا دوبوج",
    "homeLogo": "https://jdwel.com/image/teams/724.png",
    "away": "بوراتس بانيا لوكا",
    "awayLogo": "https://jdwel.com/image/teams/766.png",
    "score": "0 - 1",
    "time": "6:30 م"
  },
  {
    "home": "زرينيسكي",
    "homeLogo": "https://jdwel.com/image/teams/728.png",
    "away": "شيروكي برييغ",
    "awayLogo": "https://jdwel.com/image/teams/856.png",
    "score": "0 - 0",
    "time": "10:00 م"
  },
  {
    "home": "بوسيسيه",
    "homeLogo": "https://jdwel.com/image/teams/725.png",
    "away": "رودار برييدور",
    "awayLogo": "https://jdwel.com/image/teams/3448.png",
    "score": "0 - 0",
    "time": "10:00 م"
  },
  {
    "home": "رادنيك بيلينا",
    "homeLogo": "https://jdwel.com/image/teams/857.png",
    "away": "فيليز",
    "awayLogo": "https://jdwel.com/image/teams/855.png",
    "score": "3 - 0",
    "time": "10:00 م"
  },
  {
    "home": "شيروكي برييغ",
    "homeLogo": "https://jdwel.com/image/teams/856.png",
    "away": "سلوجا دوبوج",
    "awayLogo": "https://jdwel.com/image/teams/724.png",
    "score": "1 - 0",
    "time": "10:00 م"
  },
  {
    "home": "بوراتس بانيا لوكا",
    "homeLogo": "https://jdwel.com/image/teams/766.png",
    "away": "FK ساراييفو",
    "awayLogo": "https://jdwel.com/image/teams/858.png",
    "score": "5 - 1",
    "time": "7:45 م"
  },
  {
    "home": "جيلييزنيتشار ساراييفو",
    "homeLogo": "https://jdwel.com/image/teams/851.png",
    "away": "زرينيسكي",
    "awayLogo": "https://jdwel.com/image/teams/728.png",
    "score": "2 - 0",
    "time": "10:00 م"
  },
  {
    "home": "FK ساراييفو",
    "homeLogo": "https://jdwel.com/image/teams/858.png",
    "away": "رودار برييدور",
    "awayLogo": "https://jdwel.com/image/teams/3448.png",
    "score": "1 - 0",
    "time": "10:00 م"
  },
  {
    "home": "سلوجا دوبوج",
    "homeLogo": "https://jdwel.com/image/teams/724.png",
    "away": "جيلييزنيتشار ساراييفو",
    "awayLogo": "https://jdwel.com/image/teams/851.png",
    "score": "0 - 0",
    "time": "6:00 م"
  },
  {
    "home": "فيليز",
    "homeLogo": "https://jdwel.com/image/teams/855.png",
    "away": "بوسيسيه",
    "awayLogo": "https://jdwel.com/image/teams/725.png",
    "score": "0 - 1",
    "time": "10:00 م"
  },
  {
    "home": "بوراتس بانيا لوكا",
    "homeLogo": "https://jdwel.com/image/teams/766.png",
    "away": "شيروكي برييغ",
    "awayLogo": "https://jdwel.com/image/teams/856.png",
    "score": "5 - 1",
    "time": "7:45 م"
  },
  {
    "home": "زرينيسكي",
    "homeLogo": "https://jdwel.com/image/teams/728.png",
    "away": "رادنيك بيلينا",
    "awayLogo": "https://jdwel.com/image/teams/857.png",
    "score": "2 - 0",
    "time": "7:00 م"
  },
  {
    "home": "زرينيسكي",
    "homeLogo": "https://jdwel.com/image/teams/728.png",
    "away": "FK ساراييفو",
    "awayLogo": "https://jdwel.com/image/teams/858.png",
    "score": "2 - 0",
    "time": "9:00 م"
  },
  {
    "home": "رادنيك بيلينا",
    "homeLogo": "https://jdwel.com/image/teams/857.png",
    "away": "سلوجا دوبوج",
    "awayLogo": "https://jdwel.com/image/teams/724.png",
    "score": "0 - 0",
    "time": "10:00 م"
  },
  {
    "home": "رودار برييدور",
    "homeLogo": "https://jdwel.com/image/teams/3448.png",
    "away": "فيليز",
    "awayLogo": "https://jdwel.com/image/teams/855.png",
    "score": "1 - 3",
    "time": "7:30 م"
  },
  {
    "home": "بوسيسيه",
    "homeLogo": "https://jdwel.com/image/teams/725.png",
    "away": "زرينيسكي",
    "awayLogo": "https://jdwel.com/image/teams/728.png",
    "score": "0 - 1",
    "time": "4:00 م"
  },
  {
    "home": "شيروكي برييغ",
    "homeLogo": "https://jdwel.com/image/teams/856.png",
    "away": "FK ساراييفو",
    "awayLogo": "https://jdwel.com/image/teams/858.png",
    "score": "2 - 1",
    "time": "8:45 م"
  },
  {
    "home": "جيلييزنيتشار ساراييفو",
    "homeLogo": "https://jdwel.com/image/teams/851.png",
    "away": "بوراتس بانيا لوكا",
    "awayLogo": "https://jdwel.com/image/teams/766.png",
    "score": "3 - 2",
    "time": "10:00 م"
  },
  {
    "home": "زرينيسكي",
    "homeLogo": "https://jdwel.com/image/teams/728.png",
    "away": "سلوجا دوبوج",
    "awayLogo": "https://jdwel.com/image/teams/724.png",
    "score": "3 - 0",
    "time": "5:00 م"
  },
  {
    "home": "FK ساراييفو",
    "homeLogo": "https://jdwel.com/image/teams/858.png",
    "away": "فيليز",
    "awayLogo": "https://jdwel.com/image/teams/855.png",
    "score": "2 - 0",
    "time": "7:30 م"
  },
  {
    "home": "بوراتس بانيا لوكا",
    "homeLogo": "https://jdwel.com/image/teams/766.png",
    "away": "رادنيك بيلينا",
    "awayLogo": "https://jdwel.com/image/teams/857.png",
    "score": "5 - 1",
    "time": "9:45 م"
  },
  {
    "home": "سلوجا دوبوج",
    "homeLogo": "https://jdwel.com/image/teams/724.png",
    "away": "بوسيسيه",
    "awayLogo": "https://jdwel.com/image/teams/725.png",
    "score": "2 - 0",
    "time": "2:00 م"
  },
  {
    "home": "شيروكي برييغ",
    "homeLogo": "https://jdwel.com/image/teams/856.png",
    "away": "جيلييزنيتشار ساراييفو",
    "awayLogo": "https://jdwel.com/image/teams/851.png",
    "score": "1 - 0",
    "time": "4:00 م"
  },
  {
    "home": "زرينيسكي",
    "homeLogo": "https://jdwel.com/image/teams/728.png",
    "away": "رودار برييدور",
    "awayLogo": "https://jdwel.com/image/teams/3448.png",
    "score": "0 - 0",
    "time": "8:45 م"
  },
  {
    "home": "رادنيك بيلينا",
    "homeLogo": "https://jdwel.com/image/teams/857.png",
    "away": "شيروكي برييغ",
    "awayLogo": "https://jdwel.com/image/teams/856.png",
    "score": "0 - 0",
    "time": "7:00 م"
  },
  {
    "home": "جيلييزنيتشار ساراييفو",
    "homeLogo": "https://jdwel.com/image/teams/851.png",
    "away": "FK ساراييفو",
    "awayLogo": "https://jdwel.com/image/teams/858.png",
    "score": "2 - 0",
    "time": "7:30 م"
  },
  {
    "home": "فيليز",
    "homeLogo": "https://jdwel.com/image/teams/855.png",
    "away": "زرينيسكي",
    "awayLogo": "https://jdwel.com/image/teams/728.png",
    "score": "1 - 3",
    "time": "9:30 م"
  },
  {
    "home": "بوسيسيه",
    "homeLogo": "https://jdwel.com/image/teams/725.png",
    "away": "بوراتس بانيا لوكا",
    "awayLogo": "https://jdwel.com/image/teams/766.png",
    "score": "0 - 2",
    "time": "6:30 م"
  },
  {
    "home": "رودار برييدور",
    "homeLogo": "https://jdwel.com/image/teams/3448.png",
    "away": "سلوجا دوبوج",
    "awayLogo": "https://jdwel.com/image/teams/724.png",
    "score": "1 - 1",
    "time": "8:45 م"
  },
  {
    "home": "بوسيسيه",
    "homeLogo": "https://jdwel.com/image/teams/725.png",
    "away": "شيروكي برييغ",
    "awayLogo": "https://jdwel.com/image/teams/856.png",
    "score": "1 - 1",
    "time": "8:00 م"
  },
  {
    "home": "FK ساراييفو",
    "homeLogo": "https://jdwel.com/image/teams/858.png",
    "away": "زرينيسكي",
    "awayLogo": "https://jdwel.com/image/teams/728.png",
    "score": "0 - 0",
    "time": "6:00 م"
  },
  {
    "home": "فيليز",
    "homeLogo": "https://jdwel.com/image/teams/855.png",
    "away": "سلوجا دوبوج",
    "awayLogo": "https://jdwel.com/image/teams/724.png",
    "score": "2 - 0",
    "time": "9:45 م"
  },
  {
    "home": "رادنيك بيلينا",
    "homeLogo": "https://jdwel.com/image/teams/857.png",
    "away": "جيلييزنيتشار ساراييفو",
    "awayLogo": "https://jdwel.com/image/teams/851.png",
    "score": "1 - 0",
    "time": "6:00 م"
  },
  {
    "home": "رودار برييدور",
    "homeLogo": "https://jdwel.com/image/teams/3448.png",
    "away": "بوراتس بانيا لوكا",
    "awayLogo": "https://jdwel.com/image/teams/766.png",
    "score": "0 - 2",
    "time": "8:45 م"
  },
  {
    "home": "FK ساراييفو",
    "homeLogo": "https://jdwel.com/image/teams/858.png",
    "away": "زرينيسكي",
    "awayLogo": "https://jdwel.com/image/teams/728.png",
    "score": "1 - 1",
    "time": "7:00 م"
  },
  {
    "home": "سلوجا دوبوج",
    "homeLogo": "https://jdwel.com/image/teams/724.png",
    "away": "زرينيسكي",
    "awayLogo": "https://jdwel.com/image/teams/728.png",
    "score": "0 - 1",
    "time": "2:30 م"
  },
  {
    "home": "رادنيك بيلينا",
    "homeLogo": "https://jdwel.com/image/teams/857.png",
    "away": "FK ساراييفو",
    "awayLogo": "https://jdwel.com/image/teams/858.png",
    "score": "2 - 2",
    "time": "7:30 م"
  },
  {
    "home": "جيلييزنيتشار ساراييفو",
    "homeLogo": "https://jdwel.com/image/teams/851.png",
    "away": "بوسيسيه",
    "awayLogo": "https://jdwel.com/image/teams/725.png",
    "score": "1 - 0",
    "time": "7:30 م"
  },
  {
    "home": "بوراتس بانيا لوكا",
    "homeLogo": "https://jdwel.com/image/teams/766.png",
    "away": "فيليز",
    "awayLogo": "https://jdwel.com/image/teams/855.png",
    "score": "1 - 0",
    "time": "6:30 م"
  },
  {
    "home": "شيروكي برييغ",
    "homeLogo": "https://jdwel.com/image/teams/856.png",
    "away": "رودار برييدور",
    "awayLogo": "https://jdwel.com/image/teams/3448.png",
    "score": "1 - 0",
    "time": "8:45 م"
  },
  {
    "home": "FK ساراييفو",
    "homeLogo": "https://jdwel.com/image/teams/858.png",
    "away": "سلوجا دوبوج",
    "awayLogo": "https://jdwel.com/image/teams/724.png",
    "score": "1 - 0",
    "time": "7:00 م"
  },
  {
    "home": "رودار برييدور",
    "homeLogo": "https://jdwel.com/image/teams/3448.png",
    "away": "جيلييزنيتشار ساراييفو",
    "awayLogo": "https://jdwel.com/image/teams/851.png",
    "score": "1 - 1",
    "time": "5:00 م"
  },
  {
    "home": "فيليز",
    "homeLogo": "https://jdwel.com/image/teams/855.png",
    "away": "شيروكي برييغ",
    "awayLogo": "https://jdwel.com/image/teams/856.png",
    "score": "1 - 0",
    "time": "9:45 م"
  },
  {
    "home": "بوسيسيه",
    "homeLogo": "https://jdwel.com/image/teams/725.png",
    "away": "رادنيك بيلينا",
    "awayLogo": "https://jdwel.com/image/teams/857.png",
    "score": "4 - 0",
    "time": "5:30 م"
  },
  {
    "home": "زرينيسكي",
    "homeLogo": "https://jdwel.com/image/teams/728.png",
    "away": "بوراتس بانيا لوكا",
    "awayLogo": "https://jdwel.com/image/teams/766.png",
    "score": "2 - 1",
    "time": "8:00 م"
  },
  {
    "home": "رادنيك بيلينا",
    "homeLogo": "https://jdwel.com/image/teams/857.png",
    "away": "رودار برييدور",
    "awayLogo": "https://jdwel.com/image/teams/3448.png",
    "score": "2 - 1",
    "time": "7:00 م"
  },
  {
    "home": "شيروكي برييغ",
    "homeLogo": "https://jdwel.com/image/teams/856.png",
    "away": "زرينيسكي",
    "awayLogo": "https://jdwel.com/image/teams/728.png",
    "score": "1 - 2",
    "time": "7:30 م"
  },
  {
    "home": "بوسيسيه",
    "homeLogo": "https://jdwel.com/image/teams/725.png",
    "away": "FK ساراييفو",
    "awayLogo": "https://jdwel.com/image/teams/858.png",
    "score": "0 - 3",
    "time": "4:15 م"
  },
  {
    "home": "جيلييزنيتشار ساراييفو",
    "homeLogo": "https://jdwel.com/image/teams/851.png",
    "away": "فيليز",
    "awayLogo": "https://jdwel.com/image/teams/855.png",
    "score": "1 - 2",
    "time": "6:30 م"
  },
  {
    "home": "بوراتس بانيا لوكا",
    "homeLogo": "https://jdwel.com/image/teams/766.png",
    "away": "سلوجا دوبوج",
    "awayLogo": "https://jdwel.com/image/teams/724.png",
    "score": "2 - 1",
    "time": "9:00 م"
  },
  {
    "home": "سلوجا دوبوج",
    "homeLogo": "https://jdwel.com/image/teams/724.png",
    "away": "شيروكي برييغ",
    "awayLogo": "https://jdwel.com/image/teams/856.png",
    "score": "0 - 0",
    "time": "2:30 م"
  },
  {
    "home": "FK ساراييفو",
    "homeLogo": "https://jdwel.com/image/teams/858.png",
    "away": "بوراتس بانيا لوكا",
    "awayLogo": "https://jdwel.com/image/teams/766.png",
    "score": "1 - 0",
    "time": "7:30 م"
  },
  {
    "home": "رودار برييدور",
    "homeLogo": "https://jdwel.com/image/teams/3448.png",
    "away": "بوسيسيه",
    "awayLogo": "https://jdwel.com/image/teams/725.png",
    "score": "1 - 0",
    "time": "2:00 م"
  },
  {
    "home": "زرينيسكي",
    "homeLogo": "https://jdwel.com/image/teams/728.png",
    "away": "جيلييزنيتشار ساراييفو",
    "awayLogo": "https://jdwel.com/image/teams/851.png",
    "score": "2 - 1",
    "time": "4:15 م"
  },
  {
    "home": "فيليز",
    "homeLogo": "https://jdwel.com/image/teams/855.png",
    "away": "رادنيك بيلينا",
    "awayLogo": "https://jdwel.com/image/teams/857.png",
    "score": "1 - 0",
    "time": "6:30 م"
  },
  {
    "home": "رادنيك بيلينا",
    "homeLogo": "https://jdwel.com/image/teams/857.png",
    "away": "زرينيسكي",
    "awayLogo": "https://jdwel.com/image/teams/728.png",
    "score": "0 - 2",
    "time": "5:00 م"
  },
  {
    "home": "رودار برييدور",
    "homeLogo": "https://jdwel.com/image/teams/3448.png",
    "away": "FK ساراييفو",
    "awayLogo": "https://jdwel.com/image/teams/858.png",
    "score": "2 - 1",
    "time": "5:00 م"
  },
  {
    "home": "بوسيسيه",
    "homeLogo": "https://jdwel.com/image/teams/725.png",
    "away": "فيليز",
    "awayLogo": "https://jdwel.com/image/teams/855.png",
    "score": "0 - 0",
    "time": "4:00 م"
  },
  {
    "home": "شيروكي برييغ",
    "homeLogo": "https://jdwel.com/image/teams/856.png",
    "away": "بوراتس بانيا لوكا",
    "awayLogo": "https://jdwel.com/image/teams/766.png",
    "score": "1 - 2",
    "time": "6:15 م"
  },
  {
    "home": "سلوجا دوبوج",
    "homeLogo": "https://jdwel.com/image/teams/724.png",
    "away": "رادنيك بيلينا",
    "awayLogo": "https://jdwel.com/image/teams/857.png",
    "score": "2 - 1",
    "time": "7:00 م"
  },
  {
    "home": "بوراتس بانيا لوكا",
    "homeLogo": "https://jdwel.com/image/teams/766.png",
    "away": "جيلييزنيتشار ساراييفو",
    "awayLogo": "https://jdwel.com/image/teams/851.png",
    "score": "2 - 1",
    "time": "5:00 م"
  },
  {
    "home": "FK ساراييفو",
    "homeLogo": "https://jdwel.com/image/teams/858.png",
    "away": "شيروكي برييغ",
    "awayLogo": "https://jdwel.com/image/teams/856.png",
    "score": "0 - 0",
    "time": "5:00 م"
  },
  {
    "home": "فيليز",
    "homeLogo": "https://jdwel.com/image/teams/855.png",
    "away": "رودار برييدور",
    "awayLogo": "https://jdwel.com/image/teams/3448.png",
    "score": "1 - 0",
    "time": "7:30 م"
  },
  {
    "home": "زرينيسكي",
    "homeLogo": "https://jdwel.com/image/teams/728.png",
    "away": "بوسيسيه",
    "awayLogo": "https://jdwel.com/image/teams/725.png",
    "score": "0 - 2",
    "time": "4:00 م"
  },
  {
    "home": "فيليز",
    "homeLogo": "https://jdwel.com/image/teams/855.png",
    "away": "FK ساراييفو",
    "awayLogo": "https://jdwel.com/image/teams/858.png",
    "score": "0 - 0",
    "time": "7:30 م"
  },
  {
    "home": "رودار برييدور",
    "homeLogo": "https://jdwel.com/image/teams/3448.png",
    "away": "زرينيسكي",
    "awayLogo": "https://jdwel.com/image/teams/728.png",
    "score": "0 - 2",
    "time": "2:00 م"
  },
  {
    "home": "رادنيك بيلينا",
    "homeLogo": "https://jdwel.com/image/teams/857.png",
    "away": "بوراتس بانيا لوكا",
    "awayLogo": "https://jdwel.com/image/teams/766.png",
    "score": "0 - 1",
    "time": "5:00 م"
  },
  {
    "home": "جيلييزنيتشار ساراييفو",
    "homeLogo": "https://jdwel.com/image/teams/851.png",
    "away": "شيروكي برييغ",
    "awayLogo": "https://jdwel.com/image/teams/856.png",
    "score": "3 - 3",
    "time": "3:00 م"
  },
  {
    "home": "بوسيسيه",
    "homeLogo": "https://jdwel.com/image/teams/725.png",
    "away": "سلوجا دوبوج",
    "awayLogo": "https://jdwel.com/image/teams/724.png",
    "score": "2 - 2",
    "time": "5:00 م"
  },
  {
    "home": "FK ساراييفو",
    "homeLogo": "https://jdwel.com/image/teams/858.png",
    "away": "جيلييزنيتشار ساراييفو",
    "awayLogo": "https://jdwel.com/image/teams/851.png",
    "score": "4 - 0",
    "time": "2:00 م"
  },
  {
    "home": "زرينيسكي",
    "homeLogo": "https://jdwel.com/image/teams/728.png",
    "away": "فيليز",
    "awayLogo": "https://jdwel.com/image/teams/855.png",
    "score": "1 - 1",
    "time": "4:15 م"
  },
  {
    "home": "بوراتس بانيا لوكا",
    "homeLogo": "https://jdwel.com/image/teams/766.png",
    "away": "بوسيسيه",
    "awayLogo": "https://jdwel.com/image/teams/725.png",
    "score": "3 - 1",
    "time": "6:30 م"
  },
  {
    "home": "شيروكي برييغ",
    "homeLogo": "https://jdwel.com/image/teams/856.png",
    "away": "رادنيك بيلينا",
    "awayLogo": "https://jdwel.com/image/teams/857.png",
    "score": "1 - 3",
    "time": "5:00 م"
  },
  {
    "home": "سلوجا دوبوج",
    "homeLogo": "https://jdwel.com/image/teams/724.png",
    "away": "رودار برييدور",
    "awayLogo": "https://jdwel.com/image/teams/3448.png",
    "score": "1 - 1",
    "time": "7:00 م"
  },
  {
    "home": "سلوجا دوبوج",
    "homeLogo": "https://jdwel.com/image/teams/724.png",
    "away": "فيليز",
    "awayLogo": "https://jdwel.com/image/teams/855.png",
    "score": "1 - 2",
    "time": "5:00 م"
  },
  {
    "home": "جيلييزنيتشار ساراييفو",
    "homeLogo": "https://jdwel.com/image/teams/851.png",
    "away": "رادنيك بيلينا",
    "awayLogo": "https://jdwel.com/image/teams/857.png",
    "score": "0 - 0",
    "time": "5:00 م"
  },
  {
    "home": "شيروكي برييغ",
    "homeLogo": "https://jdwel.com/image/teams/856.png",
    "away": "بوسيسيه",
    "awayLogo": "https://jdwel.com/image/teams/725.png",
    "score": "1 - 1",
    "time": "7:30 م"
  },
  {
    "home": "بوراتس بانيا لوكا",
    "homeLogo": "https://jdwel.com/image/teams/766.png",
    "away": "رودار برييدور",
    "awayLogo": "https://jdwel.com/image/teams/3448.png",
    "score": "3 - 0",
    "time": "4:15 م"
  },
  {
    "home": "زرينيسكي",
    "homeLogo": "https://jdwel.com/image/teams/728.png",
    "away": "FK ساراييفو",
    "awayLogo": "https://jdwel.com/image/teams/858.png",
    "score": "0 - 1",
    "time": "6:30 م"
  },
  {
    "home": "جيلييزنيتشار ساراييفو",
    "homeLogo": "https://jdwel.com/image/teams/851.png",
    "away": "سلوجا دوبوج",
    "awayLogo": "https://jdwel.com/image/teams/724.png",
    "score": "0 - 0",
    "time": "5:00 م"
  },
  {
    "home": "بوراتس بانيا لوكا",
    "homeLogo": "https://jdwel.com/image/teams/766.png",
    "away": "زرينيسكي",
    "awayLogo": "https://jdwel.com/image/teams/728.png",
    "score": "0 - 1",
    "time": "4:00 م"
  },
  {
    "home": "رودار برييدور",
    "homeLogo": "https://jdwel.com/image/teams/3448.png",
    "away": "شيروكي برييغ",
    "awayLogo": "https://jdwel.com/image/teams/856.png",
    "score": "0 - 0",
    "time": "5:00 م"
  },
  {
    "home": "زرينيسكي",
    "homeLogo": "https://jdwel.com/image/teams/728.png",
    "away": "سلوجا دوبوج",
    "awayLogo": "https://jdwel.com/image/teams/724.png",
    "score": "0 - 0",
    "time": "7:00 م"
  },
  {
    "home": "FK ساراييفو",
    "homeLogo": "https://jdwel.com/image/teams/858.png",
    "away": "رادنيك بيلينا",
    "awayLogo": "https://jdwel.com/image/teams/857.png",
    "score": "0 - 0",
    "time": "9:00 م"
  },
  {
    "home": "فيليز",
    "homeLogo": "https://jdwel.com/image/teams/855.png",
    "away": "بوراتس بانيا لوكا",
    "awayLogo": "https://jdwel.com/image/teams/766.png",
    "score": "0 - 0",
    "time": "7:00 م"
  },
  {
    "home": "بوسيسيه",
    "homeLogo": "https://jdwel.com/image/teams/725.png",
    "away": "جيلييزنيتشار ساراييفو",
    "awayLogo": "https://jdwel.com/image/teams/851.png",
    "score": "0 - 0",
    "time": "2:00 م"
  },
  {
    "home": "بوراتس بانيا لوكا",
    "homeLogo": "https://jdwel.com/image/teams/766.png",
    "away": "زرينيسكي",
    "awayLogo": "https://jdwel.com/image/teams/728.png",
    "score": "0 - 0",
    "time": "2:00 ص"
  },
  {
    "home": "رادنيك بيلينا",
    "homeLogo": "https://jdwel.com/image/teams/857.png",
    "away": "بوسيسيه",
    "awayLogo": "https://jdwel.com/image/teams/725.png",
    "score": "0 - 0",
    "time": "2:00 ص"
  },
  {
    "home": "سلوجا دوبوج",
    "homeLogo": "https://jdwel.com/image/teams/724.png",
    "away": "FK ساراييفو",
    "awayLogo": "https://jdwel.com/image/teams/858.png",
    "score": "0 - 0",
    "time": "2:00 ص"
  },
  {
    "home": "جيلييزنيتشار ساراييفو",
    "homeLogo": "https://jdwel.com/image/teams/851.png",
    "away": "رودار برييدور",
    "awayLogo": "https://jdwel.com/image/teams/3448.png",
    "score": "0 - 0",
    "time": "2:00 ص"
  },
  {
    "home": "شيروكي برييغ",
    "homeLogo": "https://jdwel.com/image/teams/856.png",
    "away": "فيليز",
    "awayLogo": "https://jdwel.com/image/teams/855.png",
    "score": "0 - 0",
    "time": "2:00 ص"
  },
  {
    "home": "رودار برييدور",
    "homeLogo": "https://jdwel.com/image/teams/3448.png",
    "away": "رادنيك بيلينا",
    "awayLogo": "https://jdwel.com/image/teams/857.png",
    "score": "0 - 0",
    "time": "2:00 ص"
  },
  {
    "home": "FK ساراييفو",
    "homeLogo": "https://jdwel.com/image/teams/858.png",
    "away": "بوسيسيه",
    "awayLogo": "https://jdwel.com/image/teams/725.png",
    "score": "0 - 0",
    "time": "2:00 ص"
  },
  {
    "home": "سلوجا دوبوج",
    "homeLogo": "https://jdwel.com/image/teams/724.png",
    "away": "بوراتس بانيا لوكا",
    "awayLogo": "https://jdwel.com/image/teams/766.png",
    "score": "0 - 0",
    "time": "2:00 ص"
  },
  {
    "home": "فيليز",
    "homeLogo": "https://jdwel.com/image/teams/855.png",
    "away": "جيلييزنيتشار ساراييفو",
    "awayLogo": "https://jdwel.com/image/teams/851.png",
    "score": "0 - 0",
    "time": "2:00 ص"
  },
  {
    "home": "زرينيسكي",
    "homeLogo": "https://jdwel.com/image/teams/728.png",
    "away": "شيروكي برييغ",
    "awayLogo": "https://jdwel.com/image/teams/856.png",
    "score": "0 - 0",
    "time": "2:00 ص"
  },
  {
    "home": "بوراتس بانيا لوكا",
    "homeLogo": "https://jdwel.com/image/teams/766.png",
    "away": "FK ساراييفو",
    "awayLogo": "https://jdwel.com/image/teams/858.png",
    "score": "0 - 0",
    "time": "2:00 ص"
  },
  {
    "home": "رادنيك بيلينا",
    "homeLogo": "https://jdwel.com/image/teams/857.png",
    "away": "فيليز",
    "awayLogo": "https://jdwel.com/image/teams/855.png",
    "score": "0 - 0",
    "time": "2:00 ص"
  },
  {
    "home": "جيلييزنيتشار ساراييفو",
    "homeLogo": "https://jdwel.com/image/teams/851.png",
    "away": "زرينيسكي",
    "awayLogo": "https://jdwel.com/image/teams/728.png",
    "score": "0 - 0",
    "time": "2:00 ص"
  },
  {
    "home": "بوسيسيه",
    "homeLogo": "https://jdwel.com/image/teams/725.png",
    "away": "رودار برييدور",
    "awayLogo": "https://jdwel.com/image/teams/3448.png",
    "score": "0 - 0",
    "time": "2:00 ص"
  },
  {
    "home": "شيروكي برييغ",
    "homeLogo": "https://jdwel.com/image/teams/856.png",
    "away": "سلوجا دوبوج",
    "awayLogo": "https://jdwel.com/image/teams/724.png",
    "score": "0 - 0",
    "time": "2:00 ص"
  },
  {
    "home": "بوراتس بانيا لوكا",
    "homeLogo": "https://jdwel.com/image/teams/766.png",
    "away": "شيروكي برييغ",
    "awayLogo": "https://jdwel.com/image/teams/856.png",
    "score": "0 - 0",
    "time": "2:00 ص"
  },
  {
    "home": "FK ساراييفو",
    "homeLogo": "https://jdwel.com/image/teams/858.png",
    "away": "رودار برييدور",
    "awayLogo": "https://jdwel.com/image/teams/3448.png",
    "score": "0 - 0",
    "time": "2:00 ص"
  },
  {
    "home": "سلوجا دوبوج",
    "homeLogo": "https://jdwel.com/image/teams/724.png",
    "away": "جيلييزنيتشار ساراييفو",
    "awayLogo": "https://jdwel.com/image/teams/851.png",
    "score": "0 - 0",
    "time": "2:00 ص"
  },
  {
    "home": "فيليز",
    "homeLogo": "https://jdwel.com/image/teams/855.png",
    "away": "بوسيسيه",
    "awayLogo": "https://jdwel.com/image/teams/725.png",
    "score": "0 - 0",
    "time": "2:00 ص"
  },
  {
    "home": "زرينيسكي",
    "homeLogo": "https://jdwel.com/image/teams/728.png",
    "away": "رادنيك بيلينا",
    "awayLogo": "https://jdwel.com/image/teams/857.png",
    "score": "0 - 0",
    "time": "2:00 ص"
  },
  {
    "home": "رادنيك بيلينا",
    "homeLogo": "https://jdwel.com/image/teams/857.png",
    "away": "سلوجا دوبوج",
    "awayLogo": "https://jdwel.com/image/teams/724.png",
    "score": "0 - 0",
    "time": "2:00 ص"
  },
  {
    "home": "رودار برييدور",
    "homeLogo": "https://jdwel.com/image/teams/3448.png",
    "away": "فيليز",
    "awayLogo": "https://jdwel.com/image/teams/855.png",
    "score": "0 - 0",
    "time": "2:00 ص"
  },
  {
    "home": "جيلييزنيتشار ساراييفو",
    "homeLogo": "https://jdwel.com/image/teams/851.png",
    "away": "بوراتس بانيا لوكا",
    "awayLogo": "https://jdwel.com/image/teams/766.png",
    "score": "0 - 0",
    "time": "2:00 ص"
  },
  {
    "home": "بوسيسيه",
    "homeLogo": "https://jdwel.com/image/teams/725.png",
    "away": "زرينيسكي",
    "awayLogo": "https://jdwel.com/image/teams/728.png",
    "score": "0 - 0",
    "time": "2:00 ص"
  },
  {
    "home": "شيروكي برييغ",
    "homeLogo": "https://jdwel.com/image/teams/856.png",
    "away": "FK ساراييفو",
    "awayLogo": "https://jdwel.com/image/teams/858.png",
    "score": "0 - 0",
    "time": "2:00 ص"
  },
  {
    "home": "بوراتس بانيا لوكا",
    "homeLogo": "https://jdwel.com/image/teams/766.png",
    "away": "رادنيك بيلينا",
    "awayLogo": "https://jdwel.com/image/teams/857.png",
    "score": "0 - 0",
    "time": "2:00 ص"
  },
  {
    "home": "FK ساراييفو",
    "homeLogo": "https://jdwel.com/image/teams/858.png",
    "away": "فيليز",
    "awayLogo": "https://jdwel.com/image/teams/855.png",
    "score": "0 - 0",
    "time": "2:00 ص"
  },
  {
    "home": "سلوجا دوبوج",
    "homeLogo": "https://jdwel.com/image/teams/724.png",
    "away": "بوسيسيه",
    "awayLogo": "https://jdwel.com/image/teams/725.png",
    "score": "0 - 0",
    "time": "2:00 ص"
  },
  {
    "home": "زرينيسكي",
    "homeLogo": "https://jdwel.com/image/teams/728.png",
    "away": "رودار برييدور",
    "awayLogo": "https://jdwel.com/image/teams/3448.png",
    "score": "0 - 0",
    "time": "2:00 ص"
  },
  {
    "home": "شيروكي برييغ",
    "homeLogo": "https://jdwel.com/image/teams/856.png",
    "away": "جيلييزنيتشار ساراييفو",
    "awayLogo": "https://jdwel.com/image/teams/851.png",
    "score": "0 - 0",
    "time": "2:00 ص"
  },
  {
    "home": "رادنيك بيلينا",
    "homeLogo": "https://jdwel.com/image/teams/857.png",
    "away": "شيروكي برييغ",
    "awayLogo": "https://jdwel.com/image/teams/856.png",
    "score": "0 - 0",
    "time": "2:00 ص"
  },
  {
    "home": "رودار برييدور",
    "homeLogo": "https://jdwel.com/image/teams/3448.png",
    "away": "سلوجا دوبوج",
    "awayLogo": "https://jdwel.com/image/teams/724.png",
    "score": "0 - 0",
    "time": "2:00 ص"
  },
  {
    "home": "فيليز",
    "homeLogo": "https://jdwel.com/image/teams/855.png",
    "away": "زرينيسكي",
    "awayLogo": "https://jdwel.com/image/teams/728.png",
    "score": "0 - 0",
    "time": "2:00 ص"
  },
  {
    "home": "جيلييزنيتشار ساراييفو",
    "homeLogo": "https://jdwel.com/image/teams/851.png",
    "away": "FK ساراييفو",
    "awayLogo": "https://jdwel.com/image/teams/858.png",
    "score": "0 - 0",
    "time": "2:00 ص"
  },
  {
    "home": "بوسيسيه",
    "homeLogo": "https://jdwel.com/image/teams/725.png",
    "away": "بوراتس بانيا لوكا",
    "awayLogo": "https://jdwel.com/image/teams/766.png",
    "score": "0 - 0",
    "time": "2:00 ص"
  },
  {
    "home": "رادنيك بيلينا",
    "homeLogo": "https://jdwel.com/image/teams/857.png",
    "away": "جيلييزنيتشار ساراييفو",
    "awayLogo": "https://jdwel.com/image/teams/851.png",
    "score": "0 - 0",
    "time": "2:00 ص"
  },
  {
    "home": "رودار برييدور",
    "homeLogo": "https://jdwel.com/image/teams/3448.png",
    "away": "بوراتس بانيا لوكا",
    "awayLogo": "https://jdwel.com/image/teams/766.png",
    "score": "0 - 0",
    "time": "2:00 ص"
  },
  {
    "home": "FK ساراييفو",
    "homeLogo": "https://jdwel.com/image/teams/858.png",
    "away": "زرينيسكي",
    "awayLogo": "https://jdwel.com/image/teams/728.png",
    "score": "0 - 0",
    "time": "2:00 ص"
  },
  {
    "home": "فيليز",
    "homeLogo": "https://jdwel.com/image/teams/855.png",
    "away": "سلوجا دوبوج",
    "awayLogo": "https://jdwel.com/image/teams/724.png",
    "score": "0 - 0",
    "time": "2:00 ص"
  },
  {
    "home": "بوسيسيه",
    "homeLogo": "https://jdwel.com/image/teams/725.png",
    "away": "شيروكي برييغ",
    "awayLogo": "https://jdwel.com/image/teams/856.png",
    "score": "0 - 0",
    "time": "2:00 ص"
  },
  {
    "home": "بوراتس بانيا لوكا",
    "homeLogo": "https://jdwel.com/image/teams/766.png",
    "away": "فيليز",
    "awayLogo": "https://jdwel.com/image/teams/855.png",
    "score": "0 - 0",
    "time": "2:00 ص"
  },
  {
    "home": "رادنيك بيلينا",
    "homeLogo": "https://jdwel.com/image/teams/857.png",
    "away": "FK ساراييفو",
    "awayLogo": "https://jdwel.com/image/teams/858.png",
    "score": "0 - 0",
    "time": "2:00 ص"
  },
  {
    "home": "سلوجا دوبوج",
    "homeLogo": "https://jdwel.com/image/teams/724.png",
    "away": "زرينيسكي",
    "awayLogo": "https://jdwel.com/image/teams/728.png",
    "score": "0 - 0",
    "time": "2:00 ص"
  },
  {
    "home": "جيلييزنيتشار ساراييفو",
    "homeLogo": "https://jdwel.com/image/teams/851.png",
    "away": "بوسيسيه",
    "awayLogo": "https://jdwel.com/image/teams/725.png",
    "score": "0 - 0",
    "time": "2:00 ص"
  },
  {
    "home": "شيروكي برييغ",
    "homeLogo": "https://jdwel.com/image/teams/856.png",
    "away": "رودار برييدور",
    "awayLogo": "https://jdwel.com/image/teams/3448.png",
    "score": "0 - 0",
    "time": "2:00 ص"
  },
  {
    "home": "رودار برييدور",
    "homeLogo": "https://jdwel.com/image/teams/3448.png",
    "away": "جيلييزنيتشار ساراييفو",
    "awayLogo": "https://jdwel.com/image/teams/851.png",
    "score": "0 - 0",
    "time": "2:00 ص"
  },
  {
    "home": "FK ساراييفو",
    "homeLogo": "https://jdwel.com/image/teams/858.png",
    "away": "سلوجا دوبوج",
    "awayLogo": "https://jdwel.com/image/teams/724.png",
    "score": "0 - 0",
    "time": "2:00 ص"
  },
  {
    "home": "فيليز",
    "homeLogo": "https://jdwel.com/image/teams/855.png",
    "away": "شيروكي برييغ",
    "awayLogo": "https://jdwel.com/image/teams/856.png",
    "score": "0 - 0",
    "time": "2:00 ص"
  },
  {
    "home": "بوسيسيه",
    "homeLogo": "https://jdwel.com/image/teams/725.png",
    "away": "رادنيك بيلينا",
    "awayLogo": "https://jdwel.com/image/teams/857.png",
    "score": "0 - 0",
    "time": "2:00 ص"
  },
  {
    "home": "زرينيسكي",
    "homeLogo": "https://jdwel.com/image/teams/728.png",
    "away": "بوراتس بانيا لوكا",
    "awayLogo": "https://jdwel.com/image/teams/766.png",
    "score": "0 - 0",
    "time": "2:00 ص"
  },
  {
    "home": "بوراتس بانيا لوكا",
    "homeLogo": "https://jdwel.com/image/teams/766.png",
    "away": "سلوجا دوبوج",
    "awayLogo": "https://jdwel.com/image/teams/724.png",
    "score": "0 - 0",
    "time": "3:00 ص"
  },
  {
    "home": "رادنيك بيلينا",
    "homeLogo": "https://jdwel.com/image/teams/857.png",
    "away": "رودار برييدور",
    "awayLogo": "https://jdwel.com/image/teams/3448.png",
    "score": "0 - 0",
    "time": "3:00 ص"
  },
  {
    "home": "جيلييزنيتشار ساراييفو",
    "homeLogo": "https://jdwel.com/image/teams/851.png",
    "away": "فيليز",
    "awayLogo": "https://jdwel.com/image/teams/855.png",
    "score": "0 - 0",
    "time": "3:00 ص"
  },
  {
    "home": "بوسيسيه",
    "homeLogo": "https://jdwel.com/image/teams/725.png",
    "away": "FK ساراييفو",
    "awayLogo": "https://jdwel.com/image/teams/858.png",
    "score": "0 - 0",
    "time": "3:00 ص"
  },
  {
    "home": "شيروكي برييغ",
    "homeLogo": "https://jdwel.com/image/teams/856.png",
    "away": "زرينيسكي",
    "awayLogo": "https://jdwel.com/image/teams/728.png",
    "score": "0 - 0",
    "time": "3:00 ص"
  },
  {
    "home": "رودار برييدور",
    "homeLogo": "https://jdwel.com/image/teams/3448.png",
    "away": "بوسيسيه",
    "awayLogo": "https://jdwel.com/image/teams/725.png",
    "score": "0 - 0",
    "time": "3:00 ص"
  },
  {
    "home": "FK ساراييفو",
    "homeLogo": "https://jdwel.com/image/teams/858.png",
    "away": "بوراتس بانيا لوكا",
    "awayLogo": "https://jdwel.com/image/teams/766.png",
    "score": "0 - 0",
    "time": "3:00 ص"
  },
  {
    "home": "سلوجا دوبوج",
    "homeLogo": "https://jdwel.com/image/teams/724.png",
    "away": "شيروكي برييغ",
    "awayLogo": "https://jdwel.com/image/teams/856.png",
    "score": "0 - 0",
    "time": "3:00 ص"
  },
  {
    "home": "فيليز",
    "homeLogo": "https://jdwel.com/image/teams/855.png",
    "away": "رادنيك بيلينا",
    "awayLogo": "https://jdwel.com/image/teams/857.png",
    "score": "0 - 0",
    "time": "3:00 ص"
  },
  {
    "home": "زرينيسكي",
    "homeLogo": "https://jdwel.com/image/teams/728.png",
    "away": "جيلييزنيتشار ساراييفو",
    "awayLogo": "https://jdwel.com/image/teams/851.png",
    "score": "0 - 0",
    "time": "3:00 ص"
  },
  {
    "home": "رادنيك بيلينا",
    "homeLogo": "https://jdwel.com/image/teams/857.png",
    "away": "زرينيسكي",
    "awayLogo": "https://jdwel.com/image/teams/728.png",
    "score": "0 - 0",
    "time": "6:00 م"
  },
  {
    "home": "رودار برييدور",
    "homeLogo": "https://jdwel.com/image/teams/3448.png",
    "away": "FK ساراييفو",
    "awayLogo": "https://jdwel.com/image/teams/858.png",
    "score": "0 - 0",
    "time": "6:00 م"
  },
  {
    "home": "جيلييزنيتشار ساراييفو",
    "homeLogo": "https://jdwel.com/image/teams/851.png",
    "away": "سلوجا دوبوج",
    "awayLogo": "https://jdwel.com/image/teams/724.png",
    "score": "0 - 0",
    "time": "6:00 م"
  },
  {
    "home": "بوسيسيه",
    "homeLogo": "https://jdwel.com/image/teams/725.png",
    "away": "فيليز",
    "awayLogo": "https://jdwel.com/image/teams/855.png",
    "score": "0 - 0",
    "time": "6:00 م"
  },
  {
    "home": "شيروكي برييغ",
    "homeLogo": "https://jdwel.com/image/teams/856.png",
    "away": "بوراتس بانيا لوكا",
    "awayLogo": "https://jdwel.com/image/teams/766.png",
    "score": "0 - 0",
    "time": "6:00 م"
  },
  {
    "home": "بوراتس بانيا لوكا",
    "homeLogo": "https://jdwel.com/image/teams/766.png",
    "away": "جيلييزنيتشار ساراييفو",
    "awayLogo": "https://jdwel.com/image/teams/851.png",
    "score": "0 - 0",
    "time": "6:00 م"
  },
  {
    "home": "FK ساراييفو",
    "homeLogo": "https://jdwel.com/image/teams/858.png",
    "away": "شيروكي برييغ",
    "awayLogo": "https://jdwel.com/image/teams/856.png",
    "score": "0 - 0",
    "time": "6:00 م"
  },
  {
    "home": "سلوجا دوبوج",
    "homeLogo": "https://jdwel.com/image/teams/724.png",
    "away": "رادنيك بيلينا",
    "awayLogo": "https://jdwel.com/image/teams/857.png",
    "score": "0 - 0",
    "time": "6:00 م"
  },
  {
    "home": "فيليز",
    "homeLogo": "https://jdwel.com/image/teams/855.png",
    "away": "رودار برييدور",
    "awayLogo": "https://jdwel.com/image/teams/3448.png",
    "score": "0 - 0",
    "time": "6:00 م"
  },
  {
    "home": "زرينيسكي",
    "homeLogo": "https://jdwel.com/image/teams/728.png",
    "away": "بوسيسيه",
    "awayLogo": "https://jdwel.com/image/teams/725.png",
    "score": "0 - 0",
    "time": "6:00 م"
  },
  {
    "home": "رادنيك بيلينا",
    "homeLogo": "https://jdwel.com/image/teams/857.png",
    "away": "بوراتس بانيا لوكا",
    "awayLogo": "https://jdwel.com/image/teams/766.png",
    "score": "0 - 0",
    "time": "6:00 م"
  },
  {
    "home": "رودار برييدور",
    "homeLogo": "https://jdwel.com/image/teams/3448.png",
    "away": "زرينيسكي",
    "awayLogo": "https://jdwel.com/image/teams/728.png",
    "score": "0 - 0",
    "time": "6:00 م"
  },
  {
    "home": "فيليز",
    "homeLogo": "https://jdwel.com/image/teams/855.png",
    "away": "FK ساراييفو",
    "awayLogo": "https://jdwel.com/image/teams/858.png",
    "score": "0 - 0",
    "time": "6:00 م"
  },
  {
    "home": "جيلييزنيتشار ساراييفو",
    "homeLogo": "https://jdwel.com/image/teams/851.png",
    "away": "شيروكي برييغ",
    "awayLogo": "https://jdwel.com/image/teams/856.png",
    "score": "0 - 0",
    "time": "6:00 م"
  },
  {
    "home": "بوسيسيه",
    "homeLogo": "https://jdwel.com/image/teams/725.png",
    "away": "سلوجا دوبوج",
    "awayLogo": "https://jdwel.com/image/teams/724.png",
    "score": "0 - 0",
    "time": "6:00 م"
  },
  {
    "home": "بوراتس بانيا لوكا",
    "homeLogo": "https://jdwel.com/image/teams/766.png",
    "away": "بوسيسيه",
    "awayLogo": "https://jdwel.com/image/teams/725.png",
    "score": "0 - 0",
    "time": "6:00 م"
  },
  {
    "home": "FK ساراييفو",
    "homeLogo": "https://jdwel.com/image/teams/858.png",
    "away": "جيلييزنيتشار ساراييفو",
    "awayLogo": "https://jdwel.com/image/teams/851.png",
    "score": "0 - 0",
    "time": "6:00 م"
  },
  {
    "home": "سلوجا دوبوج",
    "homeLogo": "https://jdwel.com/image/teams/724.png",
    "away": "رودار برييدور",
    "awayLogo": "https://jdwel.com/image/teams/3448.png",
    "score": "0 - 0",
    "time": "6:00 م"
  },
  {
    "home": "زرينيسكي",
    "homeLogo": "https://jdwel.com/image/teams/728.png",
    "away": "فيليز",
    "awayLogo": "https://jdwel.com/image/teams/855.png",
    "score": "0 - 0",
    "time": "6:00 م"
  },
  {
    "home": "شيروكي برييغ",
    "homeLogo": "https://jdwel.com/image/teams/856.png",
    "away": "رادنيك بيلينا",
    "awayLogo": "https://jdwel.com/image/teams/857.png",
    "score": "0 - 0",
    "time": "6:00 م"
  }
]