[
  {
    "home": "بكين غوان",
    "homeLogo": "https://jdwel.com/image/teams/1266.png",
    "away": "ميزهو هاكا",
    "awayLogo": "https://jdwel.com/image/teams/3080.png",
    "score": "5 - 1",
    "time": "9:30 ص"
  },
  {
    "home": "تيانجين تيدا",
    "homeLogo": "https://jdwel.com/image/teams/1854.png",
    "away": "شنغهاي شنهوا",
    "awayLogo": "https://jdwel.com/image/teams/1264.png",
    "score": "1 - 3",
    "time": "9:30 ص"
  },
  {
    "home": "تشجيانغ",
    "homeLogo": "https://jdwel.com/image/teams/2754.png",
    "away": "كينغداو جونون",
    "awayLogo": "https://jdwel.com/image/teams/1268.png",
    "score": "2 - 2",
    "time": "9:30 ص"
  },
  {
    "home": "هينان",
    "homeLogo": "https://jdwel.com/image/teams/1269.png",
    "away": "يونان يوكون",
    "awayLogo": "https://jdwel.com/image/teams/2196.png",
    "score": "1 - 1",
    "time": "9:30 ص"
  },
  {
    "home": "تشينغداو ويست كوست",
    "homeLogo": "https://jdwel.com/image/teams/3082.png",
    "away": "تشانغتشون ياتاي",
    "awayLogo": "https://jdwel.com/image/teams/3077.png",
    "score": "1 - 0",
    "time": "9:30 ص"
  },
  {
    "home": "ووهان ثري تاونز",
    "homeLogo": "https://jdwel.com/image/teams/3078.png",
    "away": "شاندونغ تايشان",
    "awayLogo": "https://jdwel.com/image/teams/1441.png",
    "score": "1 - 5",
    "time": "9:30 ص"
  },
  {
    "home": "سيشوان",
    "homeLogo": "https://jdwel.com/image/teams/388.png",
    "away": "تشنغدو رونغتشنغ",
    "awayLogo": "https://jdwel.com/image/teams/4497.png",
    "score": "1 - 1",
    "time": "9:30 ص"
  },
  {
    "home": "داليان يينغبو",
    "homeLogo": "https://jdwel.com/image/teams/3009.png",
    "away": "شنغهاي بورت",
    "awayLogo": "https://jdwel.com/image/teams/1245.png",
    "score": "0 - 1",
    "time": "9:30 ص"
  },
  {
    "home": "يونان يوكون",
    "homeLogo": "https://jdwel.com/image/teams/2196.png",
    "away": "تشينغداو ويست كوست",
    "awayLogo": "https://jdwel.com/image/teams/3082.png",
    "score": "1 - 0",
    "time": "1:35 م"
  },
  {
    "home": "كينغداو جونون",
    "homeLogo": "https://jdwel.com/image/teams/1268.png",
    "away": "ووهان ثري تاونز",
    "awayLogo": "https://jdwel.com/image/teams/3078.png",
    "score": "1 - 0",
    "time": "9:30 ص"
  },
  {
    "home": "ميزهو هاكا",
    "homeLogo": "https://jdwel.com/image/teams/3080.png",
    "away": "داليان يينغبو",
    "awayLogo": "https://jdwel.com/image/teams/3009.png",
    "score": "2 - 2",
    "time": "1:35 م"
  },
  {
    "home": "تشانغتشون ياتاي",
    "homeLogo": "https://jdwel.com/image/teams/3077.png",
    "away": "بكين غوان",
    "awayLogo": "https://jdwel.com/image/teams/1266.png",
    "score": "0 - 4",
    "time": "9:30 ص"
  },
  {
    "home": "شاندونغ تايشان",
    "homeLogo": "https://jdwel.com/image/teams/1441.png",
    "away": "تيانجين تيدا",
    "awayLogo": "https://jdwel.com/image/teams/1854.png",
    "score": "2 - 1",
    "time": "9:30 ص"
  },
  {
    "home": "شنغهاي شنهوا",
    "homeLogo": "https://jdwel.com/image/teams/1264.png",
    "away": "سيشوان",
    "awayLogo": "https://jdwel.com/image/teams/388.png",
    "score": "1 - 0",
    "time": "2:00 م"
  },
  {
    "home": "تشنغدو رونغتشنغ",
    "homeLogo": "https://jdwel.com/image/teams/4497.png",
    "away": "هينان",
    "awayLogo": "https://jdwel.com/image/teams/1269.png",
    "score": "1 - 2",
    "time": "1:35 م"
  },
  {
    "home": "شنغهاي بورت",
    "homeLogo": "https://jdwel.com/image/teams/1245.png",
    "away": "تشجيانغ",
    "awayLogo": "https://jdwel.com/image/teams/2754.png",
    "score": "3 - 0",
    "time": "12:00 م"
  },
  {
    "home": "بكين غوان",
    "homeLogo": "https://jdwel.com/image/teams/1266.png",
    "away": "كينغداو جونون",
    "awayLogo": "https://jdwel.com/image/teams/1268.png",
    "score": "2 - 4",
    "time": "2:35 م"
  },
  {
    "home": "شنغهاي شنهوا",
    "homeLogo": "https://jdwel.com/image/teams/1264.png",
    "away": "داليان يينغبو",
    "awayLogo": "https://jdwel.com/image/teams/3009.png",
    "score": "2 - 2",
    "time": "2:35 م"
  },
  {
    "home": "تشينغداو ويست كوست",
    "homeLogo": "https://jdwel.com/image/teams/3082.png",
    "away": "تشنغدو رونغتشنغ",
    "awayLogo": "https://jdwel.com/image/teams/4497.png",
    "score": "2 - 2",
    "time": "1:30 م"
  },
  {
    "home": "شاندونغ تايشان",
    "homeLogo": "https://jdwel.com/image/teams/1441.png",
    "away": "شنغهاي بورت",
    "awayLogo": "https://jdwel.com/image/teams/1245.png",
    "score": "3 - 1",
    "time": "10:30 ص"
  },
  {
    "home": "هينان",
    "homeLogo": "https://jdwel.com/image/teams/1269.png",
    "away": "تشجيانغ",
    "awayLogo": "https://jdwel.com/image/teams/2754.png",
    "score": "2 - 2",
    "time": "2:00 م"
  },
  {
    "home": "تيانجين تيدا",
    "homeLogo": "https://jdwel.com/image/teams/1854.png",
    "away": "تشانغتشون ياتاي",
    "awayLogo": "https://jdwel.com/image/teams/3077.png",
    "score": "2 - 2",
    "time": "10:30 ص"
  },
  {
    "home": "ميزهو هاكا",
    "homeLogo": "https://jdwel.com/image/teams/3080.png",
    "away": "يونان يوكون",
    "awayLogo": "https://jdwel.com/image/teams/2196.png",
    "score": "1 - 4",
    "time": "2:35 م"
  },
  {
    "home": "ووهان ثري تاونز",
    "homeLogo": "https://jdwel.com/image/teams/3078.png",
    "away": "سيشوان",
    "awayLogo": "https://jdwel.com/image/teams/388.png",
    "score": "1 - 2",
    "time": "2:35 م"
  },
  {
    "home": "هينان",
    "homeLogo": "https://jdwel.com/image/teams/1269.png",
    "away": "تشانغتشون ياتاي",
    "awayLogo": "https://jdwel.com/image/teams/3077.png",
    "score": "2 - 0",
    "time": "2:35 م"
  },
  {
    "home": "داليان يينغبو",
    "homeLogo": "https://jdwel.com/image/teams/3009.png",
    "away": "ووهان ثري تاونز",
    "awayLogo": "https://jdwel.com/image/teams/3078.png",
    "score": "0 - 0",
    "time": "10:30 ص"
  },
  {
    "home": "يونان يوكون",
    "homeLogo": "https://jdwel.com/image/teams/2196.png",
    "away": "تيانجين تيدا",
    "awayLogo": "https://jdwel.com/image/teams/1854.png",
    "score": "2 - 0",
    "time": "3:00 م"
  },
  {
    "home": "تشجيانغ",
    "homeLogo": "https://jdwel.com/image/teams/2754.png",
    "away": "شاندونغ تايشان",
    "awayLogo": "https://jdwel.com/image/teams/1441.png",
    "score": "2 - 2",
    "time": "2:35 م"
  },
  {
    "home": "سيشوان",
    "homeLogo": "https://jdwel.com/image/teams/388.png",
    "away": "بكين غوان",
    "awayLogo": "https://jdwel.com/image/teams/1266.png",
    "score": "2 - 1",
    "time": "11:00 ص"
  },
  {
    "home": "تشينغداو ويست كوست",
    "homeLogo": "https://jdwel.com/image/teams/3082.png",
    "away": "شنغهاي شنهوا",
    "awayLogo": "https://jdwel.com/image/teams/1264.png",
    "score": "1 - 2",
    "time": "3:00 م"
  },
  {
    "home": "تشنغدو رونغتشنغ",
    "homeLogo": "https://jdwel.com/image/teams/4497.png",
    "away": "ميزهو هاكا",
    "awayLogo": "https://jdwel.com/image/teams/3080.png",
    "score": "3 - 1",
    "time": "2:35 م"
  },
  {
    "home": "كينغداو جونون",
    "homeLogo": "https://jdwel.com/image/teams/1268.png",
    "away": "شنغهاي بورت",
    "awayLogo": "https://jdwel.com/image/teams/1245.png",
    "score": "3 - 4",
    "time": "1:00 م"
  },
  {
    "home": "داليان يينغبو",
    "homeLogo": "https://jdwel.com/image/teams/3009.png",
    "away": "تشينغداو ويست كوست",
    "awayLogo": "https://jdwel.com/image/teams/3082.png",
    "score": "0 - 2",
    "time": "2:35 م"
  },
  {
    "home": "شاندونغ تايشان",
    "homeLogo": "https://jdwel.com/image/teams/1441.png",
    "away": "يونان يوكون",
    "awayLogo": "https://jdwel.com/image/teams/2196.png",
    "score": "1 - 1",
    "time": "2:35 م"
  },
  {
    "home": "ميزهو هاكا",
    "homeLogo": "https://jdwel.com/image/teams/3080.png",
    "away": "كينغداو جونون",
    "awayLogo": "https://jdwel.com/image/teams/1268.png",
    "score": "1 - 0",
    "time": "2:00 م"
  },
  {
    "home": "سيشوان",
    "homeLogo": "https://jdwel.com/image/teams/388.png",
    "away": "تشينغداو ويست كوست",
    "awayLogo": "https://jdwel.com/image/teams/3082.png",
    "score": "1 - 2",
    "time": "2:35 م"
  },
  {
    "home": "تيانجين تيدا",
    "homeLogo": "https://jdwel.com/image/teams/1854.png",
    "away": "هينان",
    "awayLogo": "https://jdwel.com/image/teams/1269.png",
    "score": "1 - 0",
    "time": "2:00 م"
  },
  {
    "home": "تشانغتشون ياتاي",
    "homeLogo": "https://jdwel.com/image/teams/3077.png",
    "away": "كينغداو جونون",
    "awayLogo": "https://jdwel.com/image/teams/1268.png",
    "score": "2 - 2",
    "time": "1:00 م"
  },
  {
    "home": "تشجيانغ",
    "homeLogo": "https://jdwel.com/image/teams/2754.png",
    "away": "تشنغدو رونغتشنغ",
    "awayLogo": "https://jdwel.com/image/teams/4497.png",
    "score": "3 - 3",
    "time": "3:00 م"
  },
  {
    "home": "شنغهاي بورت",
    "homeLogo": "https://jdwel.com/image/teams/1245.png",
    "away": "ووهان ثري تاونز",
    "awayLogo": "https://jdwel.com/image/teams/3078.png",
    "score": "3 - 2",
    "time": "3:00 م"
  },
  {
    "home": "بكين غوان",
    "homeLogo": "https://jdwel.com/image/teams/1266.png",
    "away": "داليان يينغبو",
    "awayLogo": "https://jdwel.com/image/teams/3009.png",
    "score": "4 - 2",
    "time": "2:35 م"
  },
  {
    "home": "شنغهاي شنهوا",
    "homeLogo": "https://jdwel.com/image/teams/1264.png",
    "away": "ميزهو هاكا",
    "awayLogo": "https://jdwel.com/image/teams/3080.png",
    "score": "6 - 1",
    "time": "1:00 م"
  },
  {
    "home": "شنغهاي شنهوا",
    "homeLogo": "https://jdwel.com/image/teams/1264.png",
    "away": "تشنغدو رونغتشنغ",
    "awayLogo": "https://jdwel.com/image/teams/4497.png",
    "score": "1 - 1",
    "time": "3:00 م"
  },
  {
    "home": "تيانجين تيدا",
    "homeLogo": "https://jdwel.com/image/teams/1854.png",
    "away": "سيشوان",
    "awayLogo": "https://jdwel.com/image/teams/388.png",
    "score": "1 - 0",
    "time": "2:35 م"
  },
  {
    "home": "بكين غوان",
    "homeLogo": "https://jdwel.com/image/teams/1266.png",
    "away": "شنغهاي بورت",
    "awayLogo": "https://jdwel.com/image/teams/1245.png",
    "score": "2 - 3",
    "time": "1:00 م"
  },
  {
    "home": "كينغداو جونون",
    "homeLogo": "https://jdwel.com/image/teams/1268.png",
    "away": "شاندونغ تايشان",
    "awayLogo": "https://jdwel.com/image/teams/1441.png",
    "score": "2 - 2",
    "time": "3:00 م"
  },
  {
    "home": "ميزهو هاكا",
    "homeLogo": "https://jdwel.com/image/teams/3080.png",
    "away": "تشينغداو ويست كوست",
    "awayLogo": "https://jdwel.com/image/teams/3082.png",
    "score": "1 - 2",
    "time": "2:35 م"
  },
  {
    "home": "تشانغتشون ياتاي",
    "homeLogo": "https://jdwel.com/image/teams/3077.png",
    "away": "تشجيانغ",
    "awayLogo": "https://jdwel.com/image/teams/2754.png",
    "score": "3 - 3",
    "time": "2:00 م"
  },
  {
    "home": "يونان يوكون",
    "homeLogo": "https://jdwel.com/image/teams/2196.png",
    "away": "داليان يينغبو",
    "awayLogo": "https://jdwel.com/image/teams/3009.png",
    "score": "1 - 1",
    "time": "3:00 م"
  },
  {
    "home": "ووهان ثري تاونز",
    "homeLogo": "https://jdwel.com/image/teams/3078.png",
    "away": "هينان",
    "awayLogo": "https://jdwel.com/image/teams/1269.png",
    "score": "2 - 5",
    "time": "2:35 م"
  },
  {
    "home": "تيانجين تيدا",
    "homeLogo": "https://jdwel.com/image/teams/1854.png",
    "away": "ووهان ثري تاونز",
    "awayLogo": "https://jdwel.com/image/teams/3078.png",
    "score": "4 - 0",
    "time": "2:35 م"
  },
  {
    "home": "داليان يينغبو",
    "homeLogo": "https://jdwel.com/image/teams/3009.png",
    "away": "سيشوان",
    "awayLogo": "https://jdwel.com/image/teams/388.png",
    "score": "2 - 1",
    "time": "2:00 م"
  },
  {
    "home": "تشينغداو ويست كوست",
    "homeLogo": "https://jdwel.com/image/teams/3082.png",
    "away": "تشجيانغ",
    "awayLogo": "https://jdwel.com/image/teams/2754.png",
    "score": "0 - 2",
    "time": "2:35 م"
  },
  {
    "home": "شنغهاي شنهوا",
    "homeLogo": "https://jdwel.com/image/teams/1264.png",
    "away": "شاندونغ تايشان",
    "awayLogo": "https://jdwel.com/image/teams/1441.png",
    "score": "3 - 3",
    "time": "3:00 م"
  },
  {
    "home": "تشنغدو رونغتشنغ",
    "homeLogo": "https://jdwel.com/image/teams/4497.png",
    "away": "تشانغتشون ياتاي",
    "awayLogo": "https://jdwel.com/image/teams/3077.png",
    "score": "1 - 0",
    "time": "2:35 م"
  },
  {
    "home": "هينان",
    "homeLogo": "https://jdwel.com/image/teams/1269.png",
    "away": "بكين غوان",
    "awayLogo": "https://jdwel.com/image/teams/1266.png",
    "score": "2 - 0",
    "time": "2:35 م"
  },
  {
    "home": "شنغهاي بورت",
    "homeLogo": "https://jdwel.com/image/teams/1245.png",
    "away": "يونان يوكون",
    "awayLogo": "https://jdwel.com/image/teams/2196.png",
    "score": "4 - 2",
    "time": "1:00 م"
  },
  {
    "home": "سيشوان",
    "homeLogo": "https://jdwel.com/image/teams/388.png",
    "away": "ميزهو هاكا",
    "awayLogo": "https://jdwel.com/image/teams/3080.png",
    "score": "2 - 0",
    "time": "2:35 م"
  },
  {
    "home": "شاندونغ تايشان",
    "homeLogo": "https://jdwel.com/image/teams/1441.png",
    "away": "بكين غوان",
    "awayLogo": "https://jdwel.com/image/teams/1266.png",
    "score": "6 - 0",
    "time": "2:35 م"
  },
  {
    "home": "ووهان ثري تاونز",
    "homeLogo": "https://jdwel.com/image/teams/3078.png",
    "away": "شنغهاي شنهوا",
    "awayLogo": "https://jdwel.com/image/teams/1264.png",
    "score": "1 - 0",
    "time": "2:00 م"
  },
  {
    "home": "يونان يوكون",
    "homeLogo": "https://jdwel.com/image/teams/2196.png",
    "away": "تشانغتشون ياتاي",
    "awayLogo": "https://jdwel.com/image/teams/3077.png",
    "score": "1 - 1",
    "time": "3:00 م"
  },
  {
    "home": "تشنغدو رونغتشنغ",
    "homeLogo": "https://jdwel.com/image/teams/4497.png",
    "away": "شنغهاي بورت",
    "awayLogo": "https://jdwel.com/image/teams/1245.png",
    "score": "4 - 1",
    "time": "2:35 م"
  },
  {
    "home": "كينغداو جونون",
    "homeLogo": "https://jdwel.com/image/teams/1268.png",
    "away": "هينان",
    "awayLogo": "https://jdwel.com/image/teams/1269.png",
    "score": "1 - 1",
    "time": "2:00 م"
  },
  {
    "home": "بكين غوان",
    "homeLogo": "https://jdwel.com/image/teams/1266.png",
    "away": "ووهان ثري تاونز",
    "awayLogo": "https://jdwel.com/image/teams/3078.png",
    "score": "4 - 0",
    "time": "3:00 م"
  },
  {
    "home": "شاندونغ تايشان",
    "homeLogo": "https://jdwel.com/image/teams/1441.png",
    "away": "تشينغداو ويست كوست",
    "awayLogo": "https://jdwel.com/image/teams/3082.png",
    "score": "3 - 2",
    "time": "3:00 م"
  },
  {
    "home": "هينان",
    "homeLogo": "https://jdwel.com/image/teams/1269.png",
    "away": "داليان يينغبو",
    "awayLogo": "https://jdwel.com/image/teams/3009.png",
    "score": "4 - 0",
    "time": "2:35 م"
  },
  {
    "home": "شنغهاي بورت",
    "homeLogo": "https://jdwel.com/image/teams/1245.png",
    "away": "تيانجين تيدا",
    "awayLogo": "https://jdwel.com/image/teams/1854.png",
    "score": "1 - 1",
    "time": "2:00 م"
  },
  {
    "home": "ميزهو هاكا",
    "homeLogo": "https://jdwel.com/image/teams/3080.png",
    "away": "تشجيانغ",
    "awayLogo": "https://jdwel.com/image/teams/2754.png",
    "score": "2 - 2",
    "time": "2:00 م"
  },
  {
    "home": "تشانغتشون ياتاي",
    "homeLogo": "https://jdwel.com/image/teams/3077.png",
    "away": "سيشوان",
    "awayLogo": "https://jdwel.com/image/teams/388.png",
    "score": "1 - 0",
    "time": "2:00 م"
  },
  {
    "home": "يونان يوكون",
    "homeLogo": "https://jdwel.com/image/teams/2196.png",
    "away": "تشنغدو رونغتشنغ",
    "awayLogo": "https://jdwel.com/image/teams/4497.png",
    "score": "1 - 5",
    "time": "2:35 م"
  },
  {
    "home": "كينغداو جونون",
    "homeLogo": "https://jdwel.com/image/teams/1268.png",
    "away": "شنغهاي شنهوا",
    "awayLogo": "https://jdwel.com/image/teams/1264.png",
    "score": "0 - 2",
    "time": "2:35 م"
  },
  {
    "home": "تشجيانغ",
    "homeLogo": "https://jdwel.com/image/teams/2754.png",
    "away": "تيانجين تيدا",
    "awayLogo": "https://jdwel.com/image/teams/1854.png",
    "score": "2 - 0",
    "time": "2:35 م"
  },
  {
    "home": "تشنغدو رونغتشنغ",
    "homeLogo": "https://jdwel.com/image/teams/4497.png",
    "away": "كينغداو جونون",
    "awayLogo": "https://jdwel.com/image/teams/1268.png",
    "score": "0 - 0",
    "time": "3:00 م"
  },
  {
    "home": "سيشوان",
    "homeLogo": "https://jdwel.com/image/teams/388.png",
    "away": "شاندونغ تايشان",
    "awayLogo": "https://jdwel.com/image/teams/1441.png",
    "score": "1 - 3",
    "time": "2:35 م"
  },
  {
    "home": "تشجيانغ",
    "homeLogo": "https://jdwel.com/image/teams/2754.png",
    "away": "شنغهاي شنهوا",
    "awayLogo": "https://jdwel.com/image/teams/1264.png",
    "score": "0 - 0",
    "time": "2:35 م"
  },
  {
    "home": "تشينغداو ويست كوست",
    "homeLogo": "https://jdwel.com/image/teams/3082.png",
    "away": "بكين غوان",
    "awayLogo": "https://jdwel.com/image/teams/1266.png",
    "score": "1 - 3",
    "time": "2:00 م"
  },
  {
    "home": "تشانغتشون ياتاي",
    "homeLogo": "https://jdwel.com/image/teams/3077.png",
    "away": "ميزهو هاكا",
    "awayLogo": "https://jdwel.com/image/teams/3080.png",
    "score": "1 - 0",
    "time": "2:00 م"
  },
  {
    "home": "تيانجين تيدا",
    "homeLogo": "https://jdwel.com/image/teams/1854.png",
    "away": "داليان يينغبو",
    "awayLogo": "https://jdwel.com/image/teams/3009.png",
    "score": "2 - 0",
    "time": "1:30 م"
  },
  {
    "home": "يونان يوكون",
    "homeLogo": "https://jdwel.com/image/teams/2196.png",
    "away": "ووهان ثري تاونز",
    "awayLogo": "https://jdwel.com/image/teams/3078.png",
    "score": "2 - 1",
    "time": "3:00 م"
  },
  {
    "home": "شنغهاي بورت",
    "homeLogo": "https://jdwel.com/image/teams/1245.png",
    "away": "هينان",
    "awayLogo": "https://jdwel.com/image/teams/1269.png",
    "score": "4 - 1",
    "time": "2:35 م"
  },
  {
    "home": "ووهان ثري تاونز",
    "homeLogo": "https://jdwel.com/image/teams/3078.png",
    "away": "ميزهو هاكا",
    "awayLogo": "https://jdwel.com/image/teams/3080.png",
    "score": "1 - 2",
    "time": "3:00 م"
  },
  {
    "home": "تشجيانغ",
    "homeLogo": "https://jdwel.com/image/teams/2754.png",
    "away": "بكين غوان",
    "awayLogo": "https://jdwel.com/image/teams/1266.png",
    "score": "3 - 4",
    "time": "2:35 م"
  },
  {
    "home": "تيانجين تيدا",
    "homeLogo": "https://jdwel.com/image/teams/1854.png",
    "away": "تشينغداو ويست كوست",
    "awayLogo": "https://jdwel.com/image/teams/3082.png",
    "score": "0 - 0",
    "time": "2:00 م"
  },
  {
    "home": "كينغداو جونون",
    "homeLogo": "https://jdwel.com/image/teams/1268.png",
    "away": "يونان يوكون",
    "awayLogo": "https://jdwel.com/image/teams/2196.png",
    "score": "5 - 1",
    "time": "3:00 م"
  },
  {
    "home": "شنغهاي شنهوا",
    "homeLogo": "https://jdwel.com/image/teams/1264.png",
    "away": "شنغهاي بورت",
    "awayLogo": "https://jdwel.com/image/teams/1245.png",
    "score": "1 - 2",
    "time": "2:35 م"
  },
  {
    "home": "شاندونغ تايشان",
    "homeLogo": "https://jdwel.com/image/teams/1441.png",
    "away": "تشانغتشون ياتاي",
    "awayLogo": "https://jdwel.com/image/teams/3077.png",
    "score": "2 - 1",
    "time": "2:00 م"
  },
  {
    "home": "هينان",
    "homeLogo": "https://jdwel.com/image/teams/1269.png",
    "away": "سيشوان",
    "awayLogo": "https://jdwel.com/image/teams/388.png",
    "score": "4 - 1",
    "time": "3:00 م"
  },
  {
    "home": "داليان يينغبو",
    "homeLogo": "https://jdwel.com/image/teams/3009.png",
    "away": "تشنغدو رونغتشنغ",
    "awayLogo": "https://jdwel.com/image/teams/4497.png",
    "score": "0 - 2",
    "time": "2:35 م"
  },
  {
    "home": "سيشوان",
    "homeLogo": "https://jdwel.com/image/teams/388.png",
    "away": "تشجيانغ",
    "awayLogo": "https://jdwel.com/image/teams/2754.png",
    "score": "2 - 4",
    "time": "3:00 م"
  },
  {
    "home": "بكين غوان",
    "homeLogo": "https://jdwel.com/image/teams/1266.png",
    "away": "تيانجين تيدا",
    "awayLogo": "https://jdwel.com/image/teams/1854.png",
    "score": "2 - 2",
    "time": "2:35 م"
  },
  {
    "home": "ووهان ثري تاونز",
    "homeLogo": "https://jdwel.com/image/teams/3078.png",
    "away": "تشانغتشون ياتاي",
    "awayLogo": "https://jdwel.com/image/teams/3077.png",
    "score": "0 - 0",
    "time": "2:35 م"
  },
  {
    "home": "داليان يينغبو",
    "homeLogo": "https://jdwel.com/image/teams/3009.png",
    "away": "كينغداو جونون",
    "awayLogo": "https://jdwel.com/image/teams/1268.png",
    "score": "2 - 0",
    "time": "2:00 م"
  },
  {
    "home": "ميزهو هاكا",
    "homeLogo": "https://jdwel.com/image/teams/3080.png",
    "away": "شنغهاي بورت",
    "awayLogo": "https://jdwel.com/image/teams/1245.png",
    "score": "2 - 4",
    "time": "3:00 م"
  },
  {
    "home": "تشينغداو ويست كوست",
    "homeLogo": "https://jdwel.com/image/teams/3082.png",
    "away": "هينان",
    "awayLogo": "https://jdwel.com/image/teams/1269.png",
    "score": "2 - 1",
    "time": "2:35 م"
  },
  {
    "home": "تشنغدو رونغتشنغ",
    "homeLogo": "https://jdwel.com/image/teams/4497.png",
    "away": "شاندونغ تايشان",
    "awayLogo": "https://jdwel.com/image/teams/1441.png",
    "score": "2 - 1",
    "time": "2:35 م"
  },
  {
    "home": "يونان يوكون",
    "homeLogo": "https://jdwel.com/image/teams/2196.png",
    "away": "شنغهاي شنهوا",
    "awayLogo": "https://jdwel.com/image/teams/1264.png",
    "score": "4 - 4",
    "time": "1:00 م"
  },
  {
    "home": "شاندونغ تايشان",
    "homeLogo": "https://jdwel.com/image/teams/1441.png",
    "away": "ميزهو هاكا",
    "awayLogo": "https://jdwel.com/image/teams/3080.png",
    "score": "3 - 0",
    "time": "3:00 م"
  },
  {
    "home": "تشجيانغ",
    "homeLogo": "https://jdwel.com/image/teams/2754.png",
    "away": "ووهان ثري تاونز",
    "awayLogo": "https://jdwel.com/image/teams/3078.png",
    "score": "3 - 2",
    "time": "2:35 م"
  },
  {
    "home": "شنغهاي شنهوا",
    "homeLogo": "https://jdwel.com/image/teams/1264.png",
    "away": "هينان",
    "awayLogo": "https://jdwel.com/image/teams/1269.png",
    "score": "3 - 2",
    "time": "2:35 م"
  },
  {
    "home": "كينغداو جونون",
    "homeLogo": "https://jdwel.com/image/teams/1268.png",
    "away": "تيانجين تيدا",
    "awayLogo": "https://jdwel.com/image/teams/1854.png",
    "score": "2 - 0",
    "time": "2:00 م"
  },
  {
    "home": "تشانغتشون ياتاي",
    "homeLogo": "https://jdwel.com/image/teams/3077.png",
    "away": "داليان يينغبو",
    "awayLogo": "https://jdwel.com/image/teams/3009.png",
    "score": "0 - 2",
    "time": "2:00 م"
  },
  {
    "home": "يونان يوكون",
    "homeLogo": "https://jdwel.com/image/teams/2196.png",
    "away": "سيشوان",
    "awayLogo": "https://jdwel.com/image/teams/388.png",
    "score": "3 - 1",
    "time": "3:00 م"
  },
  {
    "home": "تشنغدو رونغتشنغ",
    "homeLogo": "https://jdwel.com/image/teams/4497.png",
    "away": "بكين غوان",
    "awayLogo": "https://jdwel.com/image/teams/1266.png",
    "score": "2 - 0",
    "time": "2:35 م"
  },
  {
    "home": "شنغهاي بورت",
    "homeLogo": "https://jdwel.com/image/teams/1245.png",
    "away": "تشينغداو ويست كوست",
    "awayLogo": "https://jdwel.com/image/teams/3082.png",
    "score": "2 - 2",
    "time": "2:00 م"
  },
  {
    "home": "هينان",
    "homeLogo": "https://jdwel.com/image/teams/1269.png",
    "away": "ميزهو هاكا",
    "awayLogo": "https://jdwel.com/image/teams/3080.png",
    "score": "1 - 1",
    "time": "3:00 م"
  },
  {
    "home": "سيشوان",
    "homeLogo": "https://jdwel.com/image/teams/388.png",
    "away": "كينغداو جونون",
    "awayLogo": "https://jdwel.com/image/teams/1268.png",
    "score": "4 - 0",
    "time": "2:35 م"
  },
  {
    "home": "بكين غوان",
    "homeLogo": "https://jdwel.com/image/teams/1266.png",
    "away": "شنغهاي شنهوا",
    "awayLogo": "https://jdwel.com/image/teams/1264.png",
    "score": "1 - 3",
    "time": "2:35 م"
  },
  {
    "home": "داليان يينغبو",
    "homeLogo": "https://jdwel.com/image/teams/3009.png",
    "away": "شاندونغ تايشان",
    "awayLogo": "https://jdwel.com/image/teams/1441.png",
    "score": "2 - 0",
    "time": "2:00 م"
  },
  {
    "home": "تشجيانغ",
    "homeLogo": "https://jdwel.com/image/teams/2754.png",
    "away": "يونان يوكون",
    "awayLogo": "https://jdwel.com/image/teams/2196.png",
    "score": "3 - 1",
    "time": "3:00 م"
  },
  {
    "home": "تيانجين تيدا",
    "homeLogo": "https://jdwel.com/image/teams/1854.png",
    "away": "تشنغدو رونغتشنغ",
    "awayLogo": "https://jdwel.com/image/teams/4497.png",
    "score": "2 - 1",
    "time": "2:35 م"
  },
  {
    "home": "ووهان ثري تاونز",
    "homeLogo": "https://jdwel.com/image/teams/3078.png",
    "away": "تشينغداو ويست كوست",
    "awayLogo": "https://jdwel.com/image/teams/3082.png",
    "score": "1 - 1",
    "time": "2:00 م"
  },
  {
    "home": "تشانغتشون ياتاي",
    "homeLogo": "https://jdwel.com/image/teams/3077.png",
    "away": "شنغهاي بورت",
    "awayLogo": "https://jdwel.com/image/teams/1245.png",
    "score": "1 - 3",
    "time": "11:30 ص"
  },
  {
    "home": "سيشوان",
    "homeLogo": "https://jdwel.com/image/teams/388.png",
    "away": "شنغهاي بورت",
    "awayLogo": "https://jdwel.com/image/teams/1245.png",
    "score": "1 - 2",
    "time": "3:00 م"
  },
  {
    "home": "داليان يينغبو",
    "homeLogo": "https://jdwel.com/image/teams/3009.png",
    "away": "تشجيانغ",
    "awayLogo": "https://jdwel.com/image/teams/2754.png",
    "score": "1 - 0",
    "time": "2:35 م"
  },
  {
    "home": "بكين غوان",
    "homeLogo": "https://jdwel.com/image/teams/1266.png",
    "away": "يونان يوكون",
    "awayLogo": "https://jdwel.com/image/teams/2196.png",
    "score": "2 - 1",
    "time": "2:35 م"
  },
  {
    "home": "هينان",
    "homeLogo": "https://jdwel.com/image/teams/1269.png",
    "away": "شاندونغ تايشان",
    "awayLogo": "https://jdwel.com/image/teams/1441.png",
    "score": "2 - 2",
    "time": "2:00 م"
  },
  {
    "home": "ووهان ثري تاونز",
    "homeLogo": "https://jdwel.com/image/teams/3078.png",
    "away": "تشنغدو رونغتشنغ",
    "awayLogo": "https://jdwel.com/image/teams/4497.png",
    "score": "2 - 2",
    "time": "2:35 م"
  },
  {
    "home": "ميزهو هاكا",
    "homeLogo": "https://jdwel.com/image/teams/3080.png",
    "away": "تيانجين تيدا",
    "awayLogo": "https://jdwel.com/image/teams/1854.png",
    "score": "1 - 2",
    "time": "2:00 م"
  },
  {
    "home": "تشانغتشون ياتاي",
    "homeLogo": "https://jdwel.com/image/teams/3077.png",
    "away": "شنغهاي شنهوا",
    "awayLogo": "https://jdwel.com/image/teams/1264.png",
    "score": "1 - 2",
    "time": "1:30 م"
  },
  {
    "home": "تشينغداو ويست كوست",
    "homeLogo": "https://jdwel.com/image/teams/3082.png",
    "away": "كينغداو جونون",
    "awayLogo": "https://jdwel.com/image/teams/1268.png",
    "score": "1 - 0",
    "time": "1:30 م"
  },
  {
    "home": "يونان يوكون",
    "homeLogo": "https://jdwel.com/image/teams/2196.png",
    "away": "هينان",
    "awayLogo": "https://jdwel.com/image/teams/1269.png",
    "score": "2 - 1",
    "time": "3:00 م"
  },
  {
    "home": "شنغهاي بورت",
    "homeLogo": "https://jdwel.com/image/teams/1245.png",
    "away": "داليان يينغبو",
    "awayLogo": "https://jdwel.com/image/teams/3009.png",
    "score": "3 - 0",
    "time": "2:35 م"
  },
  {
    "home": "تشنغدو رونغتشنغ",
    "homeLogo": "https://jdwel.com/image/teams/4497.png",
    "away": "سيشوان",
    "awayLogo": "https://jdwel.com/image/teams/388.png",
    "score": "5 - 0",
    "time": "3:00 م"
  },
  {
    "home": "شاندونغ تايشان",
    "homeLogo": "https://jdwel.com/image/teams/1441.png",
    "away": "ووهان ثري تاونز",
    "awayLogo": "https://jdwel.com/image/teams/3078.png",
    "score": "3 - 1",
    "time": "2:35 م"
  },
  {
    "home": "تشانغتشون ياتاي",
    "homeLogo": "https://jdwel.com/image/teams/3077.png",
    "away": "تشينغداو ويست كوست",
    "awayLogo": "https://jdwel.com/image/teams/3082.png",
    "score": "1 - 0",
    "time": "2:35 م"
  },
  {
    "home": "ميزهو هاكا",
    "homeLogo": "https://jdwel.com/image/teams/3080.png",
    "away": "بكين غوان",
    "awayLogo": "https://jdwel.com/image/teams/1266.png",
    "score": "0 - 4",
    "time": "2:35 م"
  },
  {
    "home": "شنغهاي شنهوا",
    "homeLogo": "https://jdwel.com/image/teams/1264.png",
    "away": "تيانجين تيدا",
    "awayLogo": "https://jdwel.com/image/teams/1854.png",
    "score": "3 - 0",
    "time": "2:00 م"
  },
  {
    "home": "كينغداو جونون",
    "homeLogo": "https://jdwel.com/image/teams/1268.png",
    "away": "تشجيانغ",
    "awayLogo": "https://jdwel.com/image/teams/2754.png",
    "score": "0 - 3",
    "time": "2:00 م"
  },
  {
    "home": "سيشوان",
    "homeLogo": "https://jdwel.com/image/teams/388.png",
    "away": "ووهان ثري تاونز",
    "awayLogo": "https://jdwel.com/image/teams/3078.png",
    "score": "1 - 2",
    "time": "3:00 م"
  },
  {
    "home": "هينان",
    "homeLogo": "https://jdwel.com/image/teams/1269.png",
    "away": "شنغهاي بورت",
    "awayLogo": "https://jdwel.com/image/teams/1245.png",
    "score": "1 - 3",
    "time": "2:35 م"
  },
  {
    "home": "بكين غوان",
    "homeLogo": "https://jdwel.com/image/teams/1266.png",
    "away": "تشينغداو ويست كوست",
    "awayLogo": "https://jdwel.com/image/teams/3082.png",
    "score": "1 - 0",
    "time": "2:35 م"
  },
  {
    "home": "تيانجين تيدا",
    "homeLogo": "https://jdwel.com/image/teams/1854.png",
    "away": "شاندونغ تايشان",
    "awayLogo": "https://jdwel.com/image/teams/1441.png",
    "score": "1 - 0",
    "time": "3:00 م"
  },
  {
    "home": "سيشوان",
    "homeLogo": "https://jdwel.com/image/teams/388.png",
    "away": "شنغهاي شنهوا",
    "awayLogo": "https://jdwel.com/image/teams/1264.png",
    "score": "3 - 1",
    "time": "2:35 م"
  },
  {
    "home": "هينان",
    "homeLogo": "https://jdwel.com/image/teams/1269.png",
    "away": "تشنغدو رونغتشنغ",
    "awayLogo": "https://jdwel.com/image/teams/4497.png",
    "score": "3 - 2",
    "time": "2:35 م"
  },
  {
    "home": "تشينغداو ويست كوست",
    "homeLogo": "https://jdwel.com/image/teams/3082.png",
    "away": "يونان يوكون",
    "awayLogo": "https://jdwel.com/image/teams/2196.png",
    "score": "0 - 0",
    "time": "2:00 م"
  },
  {
    "home": "بكين غوان",
    "homeLogo": "https://jdwel.com/image/teams/1266.png",
    "away": "تشانغتشون ياتاي",
    "awayLogo": "https://jdwel.com/image/teams/3077.png",
    "score": "2 - 1",
    "time": "2:00 م"
  },
  {
    "home": "تشجيانغ",
    "homeLogo": "https://jdwel.com/image/teams/2754.png",
    "away": "شنغهاي بورت",
    "awayLogo": "https://jdwel.com/image/teams/1245.png",
    "score": "2 - 2",
    "time": "10:30 ص"
  },
  {
    "home": "ووهان ثري تاونز",
    "homeLogo": "https://jdwel.com/image/teams/3078.png",
    "away": "كينغداو جونون",
    "awayLogo": "https://jdwel.com/image/teams/1268.png",
    "score": "2 - 0",
    "time": "3:00 م"
  },
  {
    "home": "داليان يينغبو",
    "homeLogo": "https://jdwel.com/image/teams/3009.png",
    "away": "ميزهو هاكا",
    "awayLogo": "https://jdwel.com/image/teams/3080.png",
    "score": "1 - 0",
    "time": "2:35 م"
  },
  {
    "home": "شنغهاي بورت",
    "homeLogo": "https://jdwel.com/image/teams/1245.png",
    "away": "شاندونغ تايشان",
    "awayLogo": "https://jdwel.com/image/teams/1441.png",
    "score": "1 - 1",
    "time": "3:00 م"
  },
  {
    "home": "كينغداو جونون",
    "homeLogo": "https://jdwel.com/image/teams/1268.png",
    "away": "بكين غوان",
    "awayLogo": "https://jdwel.com/image/teams/1266.png",
    "score": "1 - 1",
    "time": "2:35 م"
  },
  {
    "home": "تشنغدو رونغتشنغ",
    "homeLogo": "https://jdwel.com/image/teams/4497.png",
    "away": "تشينغداو ويست كوست",
    "awayLogo": "https://jdwel.com/image/teams/3082.png",
    "score": "1 - 1",
    "time": "2:35 م"
  },
  {
    "home": "تشانغتشون ياتاي",
    "homeLogo": "https://jdwel.com/image/teams/3077.png",
    "away": "تيانجين تيدا",
    "awayLogo": "https://jdwel.com/image/teams/1854.png",
    "score": "1 - 2",
    "time": "2:00 م"
  },
  {
    "home": "داليان يينغبو",
    "homeLogo": "https://jdwel.com/image/teams/3009.png",
    "away": "شنغهاي شنهوا",
    "awayLogo": "https://jdwel.com/image/teams/1264.png",
    "score": "0 - 3",
    "time": "1:00 م"
  },
  {
    "home": "يونان يوكون",
    "homeLogo": "https://jdwel.com/image/teams/2196.png",
    "away": "ميزهو هاكا",
    "awayLogo": "https://jdwel.com/image/teams/3080.png",
    "score": "2 - 0",
    "time": "3:00 م"
  },
  {
    "home": "تشجيانغ",
    "homeLogo": "https://jdwel.com/image/teams/2754.png",
    "away": "هينان",
    "awayLogo": "https://jdwel.com/image/teams/1269.png",
    "score": "2 - 2",
    "time": "2:35 م"
  },
  {
    "home": "ووهان ثري تاونز",
    "homeLogo": "https://jdwel.com/image/teams/3078.png",
    "away": "داليان يينغبو",
    "awayLogo": "https://jdwel.com/image/teams/3009.png",
    "score": "2 - 2",
    "time": "2:35 م"
  },
  {
    "home": "تشانغتشون ياتاي",
    "homeLogo": "https://jdwel.com/image/teams/3077.png",
    "away": "هينان",
    "awayLogo": "https://jdwel.com/image/teams/1269.png",
    "score": "0 - 1",
    "time": "2:00 م"
  },
  {
    "home": "تيانجين تيدا",
    "homeLogo": "https://jdwel.com/image/teams/1854.png",
    "away": "يونان يوكون",
    "awayLogo": "https://jdwel.com/image/teams/2196.png",
    "score": "0 - 1",
    "time": "2:00 م"
  },
  {
    "home": "بكين غوان",
    "homeLogo": "https://jdwel.com/image/teams/1266.png",
    "away": "سيشوان",
    "awayLogo": "https://jdwel.com/image/teams/388.png",
    "score": "3 - 1",
    "time": "3:00 م"
  },
  {
    "home": "ميزهو هاكا",
    "homeLogo": "https://jdwel.com/image/teams/3080.png",
    "away": "تشنغدو رونغتشنغ",
    "awayLogo": "https://jdwel.com/image/teams/4497.png",
    "score": "0 - 4",
    "time": "2:35 م"
  },
  {
    "home": "شاندونغ تايشان",
    "homeLogo": "https://jdwel.com/image/teams/1441.png",
    "away": "تشجيانغ",
    "awayLogo": "https://jdwel.com/image/teams/2754.png",
    "score": "4 - 2",
    "time": "2:35 م"
  },
  {
    "home": "شنغهاي شنهوا",
    "homeLogo": "https://jdwel.com/image/teams/1264.png",
    "away": "تشينغداو ويست كوست",
    "awayLogo": "https://jdwel.com/image/teams/3082.png",
    "score": "4 - 0",
    "time": "2:00 م"
  },
  {
    "home": "شنغهاي بورت",
    "homeLogo": "https://jdwel.com/image/teams/1245.png",
    "away": "كينغداو جونون",
    "awayLogo": "https://jdwel.com/image/teams/1268.png",
    "score": "3 - 1",
    "time": "2:35 م"
  },
  {
    "home": "تشينغداو ويست كوست",
    "homeLogo": "https://jdwel.com/image/teams/3082.png",
    "away": "سيشوان",
    "awayLogo": "https://jdwel.com/image/teams/388.png",
    "score": "0 - 0",
    "time": "2:35 م"
  },
  {
    "home": "ميزهو هاكا",
    "homeLogo": "https://jdwel.com/image/teams/3080.png",
    "away": "شنغهاي شنهوا",
    "awayLogo": "https://jdwel.com/image/teams/1264.png",
    "score": "1 - 3",
    "time": "2:00 م"
  },
  {
    "home": "يونان يوكون",
    "homeLogo": "https://jdwel.com/image/teams/2196.png",
    "away": "شاندونغ تايشان",
    "awayLogo": "https://jdwel.com/image/teams/1441.png",
    "score": "3 - 2",
    "time": "3:00 م"
  },
  {
    "home": "كينغداو جونون",
    "homeLogo": "https://jdwel.com/image/teams/1268.png",
    "away": "تشانغتشون ياتاي",
    "awayLogo": "https://jdwel.com/image/teams/3077.png",
    "score": "3 - 0",
    "time": "2:35 م"
  },
  {
    "home": "تشنغدو رونغتشنغ",
    "homeLogo": "https://jdwel.com/image/teams/4497.png",
    "away": "تشجيانغ",
    "awayLogo": "https://jdwel.com/image/teams/2754.png",
    "score": "2 - 1",
    "time": "2:35 م"
  },
  {
    "home": "هينان",
    "homeLogo": "https://jdwel.com/image/teams/1269.png",
    "away": "تيانجين تيدا",
    "awayLogo": "https://jdwel.com/image/teams/1854.png",
    "score": "3 - 4",
    "time": "2:00 م"
  },
  {
    "home": "ووهان ثري تاونز",
    "homeLogo": "https://jdwel.com/image/teams/3078.png",
    "away": "شنغهاي بورت",
    "awayLogo": "https://jdwel.com/image/teams/1245.png",
    "score": "0 - 2",
    "time": "2:00 م"
  },
  {
    "home": "داليان يينغبو",
    "homeLogo": "https://jdwel.com/image/teams/3009.png",
    "away": "بكين غوان",
    "awayLogo": "https://jdwel.com/image/teams/1266.png",
    "score": "0 - 2",
    "time": "10:30 ص"
  },
  {
    "home": "تشنغدو رونغتشنغ",
    "homeLogo": "https://jdwel.com/image/teams/4497.png",
    "away": "شنغهاي شنهوا",
    "awayLogo": "https://jdwel.com/image/teams/1264.png",
    "score": "1 - 0",
    "time": "2:35 م"
  },
  {
    "home": "تشينغداو ويست كوست",
    "homeLogo": "https://jdwel.com/image/teams/3082.png",
    "away": "ميزهو هاكا",
    "awayLogo": "https://jdwel.com/image/teams/3080.png",
    "score": "3 - 1",
    "time": "2:00 م"
  },
  {
    "home": "شاندونغ تايشان",
    "homeLogo": "https://jdwel.com/image/teams/1441.png",
    "away": "كينغداو جونون",
    "awayLogo": "https://jdwel.com/image/teams/1268.png",
    "score": "1 - 1",
    "time": "2:35 م"
  },
  {
    "home": "شنغهاي بورت",
    "homeLogo": "https://jdwel.com/image/teams/1245.png",
    "away": "بكين غوان",
    "awayLogo": "https://jdwel.com/image/teams/1266.png",
    "score": "1 - 2",
    "time": "2:35 م"
  },
  {
    "home": "تشجيانغ",
    "homeLogo": "https://jdwel.com/image/teams/2754.png",
    "away": "تشانغتشون ياتاي",
    "awayLogo": "https://jdwel.com/image/teams/3077.png",
    "score": "4 - 2",
    "time": "2:00 م"
  },
  {
    "home": "هينان",
    "homeLogo": "https://jdwel.com/image/teams/1269.png",
    "away": "ووهان ثري تاونز",
    "awayLogo": "https://jdwel.com/image/teams/3078.png",
    "score": "1 - 2",
    "time": "2:00 م"
  },
  {
    "home": "سيشوان",
    "homeLogo": "https://jdwel.com/image/teams/388.png",
    "away": "تيانجين تيدا",
    "awayLogo": "https://jdwel.com/image/teams/1854.png",
    "score": "1 - 0",
    "time": "1:30 م"
  },
  {
    "home": "داليان يينغبو",
    "homeLogo": "https://jdwel.com/image/teams/3009.png",
    "away": "يونان يوكون",
    "awayLogo": "https://jdwel.com/image/teams/2196.png",
    "score": "3 - 2",
    "time": "10:30 ص"
  },
  {
    "home": "تشجيانغ",
    "homeLogo": "https://jdwel.com/image/teams/2754.png",
    "away": "تشينغداو ويست كوست",
    "awayLogo": "https://jdwel.com/image/teams/3082.png",
    "score": "2 - 1",
    "time": "3:00 م"
  },
  {
    "home": "كينغداو جونون",
    "homeLogo": "https://jdwel.com/image/teams/1268.png",
    "away": "ميزهو هاكا",
    "awayLogo": "https://jdwel.com/image/teams/3080.png",
    "score": "1 - 1",
    "time": "2:35 م"
  },
  {
    "home": "ووهان ثري تاونز",
    "homeLogo": "https://jdwel.com/image/teams/3078.png",
    "away": "تيانجين تيدا",
    "awayLogo": "https://jdwel.com/image/teams/1854.png",
    "score": "2 - 1",
    "time": "2:00 م"
  },
  {
    "home": "شاندونغ تايشان",
    "homeLogo": "https://jdwel.com/image/teams/1441.png",
    "away": "شنغهاي شنهوا",
    "awayLogo": "https://jdwel.com/image/teams/1264.png",
    "score": "0 - 1",
    "time": "2:35 م"
  },
  {
    "home": "سيشوان",
    "homeLogo": "https://jdwel.com/image/teams/388.png",
    "away": "داليان يينغبو",
    "awayLogo": "https://jdwel.com/image/teams/3009.png",
    "score": "1 - 1",
    "time": "2:00 م"
  },
  {
    "home": "تشانغتشون ياتاي",
    "homeLogo": "https://jdwel.com/image/teams/3077.png",
    "away": "تشنغدو رونغتشنغ",
    "awayLogo": "https://jdwel.com/image/teams/4497.png",
    "score": "1 - 2",
    "time": "10:30 ص"
  },
  {
    "home": "يونان يوكون",
    "homeLogo": "https://jdwel.com/image/teams/2196.png",
    "away": "شنغهاي بورت",
    "awayLogo": "https://jdwel.com/image/teams/1245.png",
    "score": "2 - 3",
    "time": "3:00 م"
  },
  {
    "home": "بكين غوان",
    "homeLogo": "https://jdwel.com/image/teams/1266.png",
    "away": "هينان",
    "awayLogo": "https://jdwel.com/image/teams/1269.png",
    "score": "1 - 0",
    "time": "2:35 م"
  },
  {
    "home": "تيانجين تيدا",
    "homeLogo": "https://jdwel.com/image/teams/1854.png",
    "away": "تشجيانغ",
    "awayLogo": "https://jdwel.com/image/teams/2754.png",
    "score": "2 - 0",
    "time": "1:35 م"
  },
  {
    "home": "شنغهاي بورت",
    "homeLogo": "https://jdwel.com/image/teams/1245.png",
    "away": "تشنغدو رونغتشنغ",
    "awayLogo": "https://jdwel.com/image/teams/4497.png",
    "score": "1 - 3",
    "time": "1:35 م"
  },
  {
    "home": "ميزهو هاكا",
    "homeLogo": "https://jdwel.com/image/teams/3080.png",
    "away": "سيشوان",
    "awayLogo": "https://jdwel.com/image/teams/388.png",
    "score": "3 - 0",
    "time": "1:00 م"
  },
  {
    "home": "هينان",
    "homeLogo": "https://jdwel.com/image/teams/1269.png",
    "away": "كينغداو جونون",
    "awayLogo": "https://jdwel.com/image/teams/1268.png",
    "score": "3 - 1",
    "time": "12:30 م"
  },
  {
    "home": "تشينغداو ويست كوست",
    "homeLogo": "https://jdwel.com/image/teams/3082.png",
    "away": "داليان يينغبو",
    "awayLogo": "https://jdwel.com/image/teams/3009.png",
    "score": "2 - 0",
    "time": "12:30 م"
  },
  {
    "home": "تشانغتشون ياتاي",
    "homeLogo": "https://jdwel.com/image/teams/3077.png",
    "away": "يونان يوكون",
    "awayLogo": "https://jdwel.com/image/teams/2196.png",
    "score": "0 - 0",
    "time": "9:30 ص"
  },
  {
    "home": "بكين غوان",
    "homeLogo": "https://jdwel.com/image/teams/1266.png",
    "away": "شاندونغ تايشان",
    "awayLogo": "https://jdwel.com/image/teams/1441.png",
    "score": "6 - 1",
    "time": "1:35 م"
  },
  {
    "home": "شنغهاي شنهوا",
    "homeLogo": "https://jdwel.com/image/teams/1264.png",
    "away": "ووهان ثري تاونز",
    "awayLogo": "https://jdwel.com/image/teams/3078.png",
    "score": "2 - 0",
    "time": "1:00 م"
  },
  {
    "home": "شنغهاي شنهوا",
    "homeLogo": "https://jdwel.com/image/teams/1264.png",
    "away": "كينغداو جونون",
    "awayLogo": "https://jdwel.com/image/teams/1268.png",
    "score": "3 - 2",
    "time": "2:00 م"
  },
  {
    "home": "تشنغدو رونغتشنغ",
    "homeLogo": "https://jdwel.com/image/teams/4497.png",
    "away": "يونان يوكون",
    "awayLogo": "https://jdwel.com/image/teams/2196.png",
    "score": "1 - 1",
    "time": "1:35 م"
  },
  {
    "home": "داليان يينغبو",
    "homeLogo": "https://jdwel.com/image/teams/3009.png",
    "away": "هينان",
    "awayLogo": "https://jdwel.com/image/teams/1269.png",
    "score": "1 - 0",
    "time": "1:00 م"
  },
  {
    "home": "تشجيانغ",
    "homeLogo": "https://jdwel.com/image/teams/2754.png",
    "away": "ميزهو هاكا",
    "awayLogo": "https://jdwel.com/image/teams/3080.png",
    "score": "2 - 2",
    "time": "1:00 م"
  },
  {
    "home": "تيانجين تيدا",
    "homeLogo": "https://jdwel.com/image/teams/1854.png",
    "away": "شنغهاي بورت",
    "awayLogo": "https://jdwel.com/image/teams/1245.png",
    "score": "1 - 4",
    "time": "12:00 م"
  },
  {
    "home": "سيشوان",
    "homeLogo": "https://jdwel.com/image/teams/388.png",
    "away": "تشانغتشون ياتاي",
    "awayLogo": "https://jdwel.com/image/teams/3077.png",
    "score": "3 - 1",
    "time": "2:00 م"
  },
  {
    "home": "ووهان ثري تاونز",
    "homeLogo": "https://jdwel.com/image/teams/3078.png",
    "away": "بكين غوان",
    "awayLogo": "https://jdwel.com/image/teams/1266.png",
    "score": "4 - 4",
    "time": "1:35 م"
  },
  {
    "home": "تشينغداو ويست كوست",
    "homeLogo": "https://jdwel.com/image/teams/3082.png",
    "away": "شاندونغ تايشان",
    "awayLogo": "https://jdwel.com/image/teams/1441.png",
    "score": "1 - 5",
    "time": "12:30 م"
  },
  {
    "home": "شنغهاي شنهوا",
    "homeLogo": "https://jdwel.com/image/teams/1264.png",
    "away": "تشجيانغ",
    "awayLogo": "https://jdwel.com/image/teams/2754.png",
    "score": "3 - 2",
    "time": "2:00 م"
  },
  {
    "home": "ووهان ثري تاونز",
    "homeLogo": "https://jdwel.com/image/teams/3078.png",
    "away": "يونان يوكون",
    "awayLogo": "https://jdwel.com/image/teams/2196.png",
    "score": "3 - 1",
    "time": "1:35 م"
  },
  {
    "home": "كينغداو جونون",
    "homeLogo": "https://jdwel.com/image/teams/1268.png",
    "away": "تشنغدو رونغتشنغ",
    "awayLogo": "https://jdwel.com/image/teams/4497.png",
    "score": "0 - 1",
    "time": "1:00 م"
  },
  {
    "home": "داليان يينغبو",
    "homeLogo": "https://jdwel.com/image/teams/3009.png",
    "away": "تيانجين تيدا",
    "awayLogo": "https://jdwel.com/image/teams/1854.png",
    "score": "1 - 1",
    "time": "9:30 ص"
  },
  {
    "home": "شاندونغ تايشان",
    "homeLogo": "https://jdwel.com/image/teams/1441.png",
    "away": "سيشوان",
    "awayLogo": "https://jdwel.com/image/teams/388.png",
    "score": "4 - 0",
    "time": "1:35 م"
  },
  {
    "home": "ميزهو هاكا",
    "homeLogo": "https://jdwel.com/image/teams/3080.png",
    "away": "تشانغتشون ياتاي",
    "awayLogo": "https://jdwel.com/image/teams/3077.png",
    "score": "1 - 3",
    "time": "1:35 م"
  },
  {
    "home": "يونان يوكون",
    "homeLogo": "https://jdwel.com/image/teams/2196.png",
    "away": "كينغداو جونون",
    "awayLogo": "https://jdwel.com/image/teams/1268.png",
    "score": "1 - 0",
    "time": "2:00 م"
  },
  {
    "home": "شنغهاي بورت",
    "homeLogo": "https://jdwel.com/image/teams/1245.png",
    "away": "شنغهاي شنهوا",
    "awayLogo": "https://jdwel.com/image/teams/1264.png",
    "score": "1 - 1",
    "time": "1:35 م"
  },
  {
    "home": "بكين غوان",
    "homeLogo": "https://jdwel.com/image/teams/1266.png",
    "away": "تشجيانغ",
    "awayLogo": "https://jdwel.com/image/teams/2754.png",
    "score": "2 - 0",
    "time": "1:35 م"
  },
  {
    "home": "ميزهو هاكا",
    "homeLogo": "https://jdwel.com/image/teams/3080.png",
    "away": "ووهان ثري تاونز",
    "awayLogo": "https://jdwel.com/image/teams/3078.png",
    "score": "3 - 1",
    "time": "1:00 م"
  },
  {
    "home": "تشنغدو رونغتشنغ",
    "homeLogo": "https://jdwel.com/image/teams/4497.png",
    "away": "داليان يينغبو",
    "awayLogo": "https://jdwel.com/image/teams/3009.png",
    "score": "2 - 0",
    "time": "1:00 م"
  },
  {
    "home": "تشينغداو ويست كوست",
    "homeLogo": "https://jdwel.com/image/teams/3082.png",
    "away": "تيانجين تيدا",
    "awayLogo": "https://jdwel.com/image/teams/1854.png",
    "score": "2 - 2",
    "time": "12:30 م"
  },
  {
    "home": "تشانغتشون ياتاي",
    "homeLogo": "https://jdwel.com/image/teams/3077.png",
    "away": "شاندونغ تايشان",
    "awayLogo": "https://jdwel.com/image/teams/1441.png",
    "score": "1 - 2",
    "time": "9:30 ص"
  },
  {
    "home": "سيشوان",
    "homeLogo": "https://jdwel.com/image/teams/388.png",
    "away": "هينان",
    "awayLogo": "https://jdwel.com/image/teams/1269.png",
    "score": "1 - 3",
    "time": "1:35 م"
  },
  {
    "home": "شنغهاي بورت",
    "homeLogo": "https://jdwel.com/image/teams/1245.png",
    "away": "ميزهو هاكا",
    "awayLogo": "https://jdwel.com/image/teams/3080.png",
    "score": "2 - 1",
    "time": "2:00 م"
  },
  {
    "home": "شاندونغ تايشان",
    "homeLogo": "https://jdwel.com/image/teams/1441.png",
    "away": "تشنغدو رونغتشنغ",
    "awayLogo": "https://jdwel.com/image/teams/4497.png",
    "score": "0 - 3",
    "time": "1:35 م"
  },
  {
    "home": "تيانجين تيدا",
    "homeLogo": "https://jdwel.com/image/teams/1854.png",
    "away": "بكين غوان",
    "awayLogo": "https://jdwel.com/image/teams/1266.png",
    "score": "2 - 2",
    "time": "1:35 م"
  },
  {
    "home": "كينغداو جونون",
    "homeLogo": "https://jdwel.com/image/teams/1268.png",
    "away": "داليان يينغبو",
    "awayLogo": "https://jdwel.com/image/teams/3009.png",
    "score": "1 - 1",
    "time": "1:00 م"
  },
  {
    "home": "شنغهاي شنهوا",
    "homeLogo": "https://jdwel.com/image/teams/1264.png",
    "away": "يونان يوكون",
    "awayLogo": "https://jdwel.com/image/teams/2196.png",
    "score": "3 - 1",
    "time": "12:00 م"
  },
  {
    "home": "تشانغتشون ياتاي",
    "homeLogo": "https://jdwel.com/image/teams/3077.png",
    "away": "ووهان ثري تاونز",
    "awayLogo": "https://jdwel.com/image/teams/3078.png",
    "score": "1 - 1",
    "time": "9:30 ص"
  },
  {
    "home": "تشجيانغ",
    "homeLogo": "https://jdwel.com/image/teams/2754.png",
    "away": "سيشوان",
    "awayLogo": "https://jdwel.com/image/teams/388.png",
    "score": "3 - 0",
    "time": "1:35 م"
  },
  {
    "home": "هينان",
    "homeLogo": "https://jdwel.com/image/teams/1269.png",
    "away": "تشينغداو ويست كوست",
    "awayLogo": "https://jdwel.com/image/teams/3082.png",
    "score": "2 - 3",
    "time": "1:00 م"
  },
  {
    "home": "بكين غوان",
    "homeLogo": "https://jdwel.com/image/teams/1266.png",
    "away": "تشنغدو رونغتشنغ",
    "awayLogo": "https://jdwel.com/image/teams/4497.png",
    "score": "1 - 1",
    "time": "1:35 م"
  },
  {
    "home": "ميزهو هاكا",
    "homeLogo": "https://jdwel.com/image/teams/3080.png",
    "away": "شاندونغ تايشان",
    "awayLogo": "https://jdwel.com/image/teams/1441.png",
    "score": "3 - 4",
    "time": "1:00 م"
  },
  {
    "home": "هينان",
    "homeLogo": "https://jdwel.com/image/teams/1269.png",
    "away": "شنغهاي شنهوا",
    "awayLogo": "https://jdwel.com/image/teams/1264.png",
    "score": "1 - 3",
    "time": "12:00 م"
  },
  {
    "home": "داليان يينغبو",
    "homeLogo": "https://jdwel.com/image/teams/3009.png",
    "away": "تشانغتشون ياتاي",
    "awayLogo": "https://jdwel.com/image/teams/3077.png",
    "score": "2 - 0",
    "time": "9:30 ص"
  },
  {
    "home": "تيانجين تيدا",
    "homeLogo": "https://jdwel.com/image/teams/1854.png",
    "away": "كينغداو جونون",
    "awayLogo": "https://jdwel.com/image/teams/1268.png",
    "score": "1 - 0",
    "time": "9:30 ص"
  },
  {
    "home": "سيشوان",
    "homeLogo": "https://jdwel.com/image/teams/388.png",
    "away": "يونان يوكون",
    "awayLogo": "https://jdwel.com/image/teams/2196.png",
    "score": "3 - 4",
    "time": "2:00 م"
  },
  {
    "home": "ووهان ثري تاونز",
    "homeLogo": "https://jdwel.com/image/teams/3078.png",
    "away": "تشجيانغ",
    "awayLogo": "https://jdwel.com/image/teams/2754.png",
    "score": "0 - 4",
    "time": "1:35 م"
  },
  {
    "home": "تشينغداو ويست كوست",
    "homeLogo": "https://jdwel.com/image/teams/3082.png",
    "away": "شنغهاي بورت",
    "awayLogo": "https://jdwel.com/image/teams/1245.png",
    "score": "3 - 3",
    "time": "1:00 م"
  },
  {
    "home": "تشينغداو ويست كوست",
    "homeLogo": "https://jdwel.com/image/teams/3082.png",
    "away": "ووهان ثري تاونز",
    "awayLogo": "https://jdwel.com/image/teams/3078.png",
    "score": "2 - 0",
    "time": "8:00 ص"
  },
  {
    "home": "تشنغدو رونغتشنغ",
    "homeLogo": "https://jdwel.com/image/teams/4497.png",
    "away": "تيانجين تيدا",
    "awayLogo": "https://jdwel.com/image/teams/1854.png",
    "score": "1 - 2",
    "time": "12:30 م"
  },
  {
    "home": "يونان يوكون",
    "homeLogo": "https://jdwel.com/image/teams/2196.png",
    "away": "تشجيانغ",
    "awayLogo": "https://jdwel.com/image/teams/2754.png",
    "score": "1 - 1",
    "time": "2:00 م"
  },
  {
    "home": "ميزهو هاكا",
    "homeLogo": "https://jdwel.com/image/teams/3080.png",
    "away": "هينان",
    "awayLogo": "https://jdwel.com/image/teams/1269.png",
    "score": "2 - 1",
    "time": "1:35 م"
  },
  {
    "home": "شنغهاي شنهوا",
    "homeLogo": "https://jdwel.com/image/teams/1264.png",
    "away": "بكين غوان",
    "awayLogo": "https://jdwel.com/image/teams/1266.png",
    "score": "2 - 2",
    "time": "1:35 م"
  },
  {
    "home": "كينغداو جونون",
    "homeLogo": "https://jdwel.com/image/teams/1268.png",
    "away": "سيشوان",
    "awayLogo": "https://jdwel.com/image/teams/388.png",
    "score": "0 - 1",
    "time": "9:30 ص"
  },
  {
    "home": "شنغهاي بورت",
    "homeLogo": "https://jdwel.com/image/teams/1245.png",
    "away": "تشانغتشون ياتاي",
    "awayLogo": "https://jdwel.com/image/teams/3077.png",
    "score": "2 - 0",
    "time": "1:35 م"
  },
  {
    "home": "شاندونغ تايشان",
    "homeLogo": "https://jdwel.com/image/teams/1441.png",
    "away": "داليان يينغبو",
    "awayLogo": "https://jdwel.com/image/teams/3009.png",
    "score": "4 - 1",
    "time": "9:30 ص"
  },
  {
    "home": "شنغهاي بورت",
    "homeLogo": "https://jdwel.com/image/teams/1245.png",
    "away": "سيشوان",
    "awayLogo": "https://jdwel.com/image/teams/388.png",
    "score": "3 - 1",
    "time": "1:35 م"
  },
  {
    "home": "كينغداو جونون",
    "homeLogo": "https://jdwel.com/image/teams/1268.png",
    "away": "تشينغداو ويست كوست",
    "awayLogo": "https://jdwel.com/image/teams/3082.png",
    "score": "2 - 2",
    "time": "9:30 ص"
  },
  {
    "home": "تشجيانغ",
    "homeLogo": "https://jdwel.com/image/teams/2754.png",
    "away": "داليان يينغبو",
    "awayLogo": "https://jdwel.com/image/teams/3009.png",
    "score": "1 - 1",
    "time": "9:30 ص"
  },
  {
    "home": "شاندونغ تايشان",
    "homeLogo": "https://jdwel.com/image/teams/1441.png",
    "away": "هينان",
    "awayLogo": "https://jdwel.com/image/teams/1269.png",
    "score": "0 - 0",
    "time": "9:30 ص"
  },
  {
    "home": "تيانجين تيدا",
    "homeLogo": "https://jdwel.com/image/teams/1854.png",
    "away": "ميزهو هاكا",
    "awayLogo": "https://jdwel.com/image/teams/3080.png",
    "score": "2 - 2",
    "time": "9:30 ص"
  },
  {
    "home": "شنغهاي شنهوا",
    "homeLogo": "https://jdwel.com/image/teams/1264.png",
    "away": "تشانغتشون ياتاي",
    "awayLogo": "https://jdwel.com/image/teams/3077.png",
    "score": "2 - 1",
    "time": "2:00 م"
  },
  {
    "home": "يونان يوكون",
    "homeLogo": "https://jdwel.com/image/teams/2196.png",
    "away": "بكين غوان",
    "awayLogo": "https://jdwel.com/image/teams/1266.png",
    "score": "0 - 2",
    "time": "2:00 م"
  },
  {
    "home": "تشنغدو رونغتشنغ",
    "homeLogo": "https://jdwel.com/image/teams/4497.png",
    "away": "ووهان ثري تاونز",
    "awayLogo": "https://jdwel.com/image/teams/3078.png",
    "score": "1 - 0",
    "time": "1:35 م"
  }
]