[
  {
    "date": "السبت 2025/09/27",
    "round": "",
    "status": "انتهت",
    "home": "أتلتيك سانت جست",
    "homeLogo": "https://jdwel.com/image/teams/4429.png",
    "away": "أتلتيكو كالاتايود",
    "awayLogo": "https://jdwel.com/image/teams/4430.png",
    "score": "3 - 0",
    "time": "5:30 م"
  },
  {
    "date": "السبت 2025/09/27",
    "round": "",
    "status": "انتهت",
    "home": "جيتكسو",
    "homeLogo": "https://jdwel.com/image/teams/4431.png",
    "away": "بيتيس",
    "awayLogo": "https://jdwel.com/image/teams/4432.png",
    "score": "0 - 0",
    "time": "6:00 م"
  },
  {
    "date": "السبت 2025/09/27",
    "round": "",
    "status": "انتهت",
    "home": "بويرتو دي فيغا",
    "homeLogo": "https://jdwel.com/image/teams/4433.png",
    "away": "ألبيريت",
    "awayLogo": "https://jdwel.com/image/teams/4434.png",
    "score": "4 - 0",
    "time": "6:15 م"
  },
  {
    "date": "السبت 2025/09/27",
    "round": "",
    "status": "انتهت",
    "home": "مانيسيس",
    "homeLogo": "https://jdwel.com/image/teams/1053.png",
    "away": "لوس غاريس",
    "awayLogo": "https://jdwel.com/image/teams/4435.png",
    "score": "2 - 0",
    "time": "7:00 م"
  },
  {
    "date": "السبت 2025/09/27",
    "round": "",
    "status": "انتهت",
    "home": "سبورتينغ دي سيوتا",
    "homeLogo": "https://jdwel.com/image/teams/4436.png",
    "away": "ماراسينا",
    "awayLogo": "https://jdwel.com/image/teams/4437.png",
    "score": "1 - 1",
    "time": "7:00 م"
  },
  {
    "date": "السبت 2025/09/27",
    "round": "",
    "status": "انتهت",
    "home": "تكستيل إسكودو",
    "homeLogo": "https://jdwel.com/image/teams/4438.png",
    "away": "نيجريرا",
    "awayLogo": "https://jdwel.com/image/teams/4439.png",
    "score": "2 - 1",
    "time": "7:00 م"
  },
  {
    "date": "السبت 2025/09/27",
    "round": "",
    "status": "انتهت",
    "home": "كامباناريو",
    "homeLogo": "https://jdwel.com/image/teams/4441.png",
    "away": "يونكوس",
    "awayLogo": "https://jdwel.com/image/teams/4440.png",
    "score": "0 - 0",
    "time": "7:45 م"
  },
  {
    "date": "السبت 2025/09/27",
    "round": "",
    "status": "انتهت",
    "home": "إنتر دي فالديمورو",
    "homeLogo": "https://jdwel.com/image/teams/4444.png",
    "away": "أونيفيرسيتاريو",
    "awayLogo": "https://jdwel.com/image/teams/4445.png",
    "score": "1 - 1",
    "time": "9:00 م"
  },
  {
    "date": "السبت 2025/09/27",
    "round": "",
    "status": "انتهت",
    "home": "أتلتيكو ميليلا",
    "homeLogo": "https://jdwel.com/image/teams/4442.png",
    "away": "بالما ديل ريو",
    "awayLogo": "https://jdwel.com/image/teams/4443.png",
    "score": "0 - 5",
    "time": "9:00 م"
  },
  {
    "date": "السبت 2025/09/27",
    "round": "",
    "status": "انتهت",
    "home": "سانت جوردي",
    "homeLogo": "https://jdwel.com/image/teams/4446.png",
    "away": "لورديس",
    "awayLogo": "https://jdwel.com/image/teams/4447.png",
    "score": "1 - 0",
    "time": "9:00 م"
  },
  {
    "date": "السبت 2025/10/04",
    "round": "",
    "status": "انتهت",
    "home": "ألبيريت",
    "homeLogo": "https://jdwel.com/image/teams/4434.png",
    "away": "بويرتو دي فيغا",
    "awayLogo": "https://jdwel.com/image/teams/4433.png",
    "score": "1 - 1",
    "time": "5:45 م"
  },
  {
    "date": "السبت 2025/10/04",
    "round": "",
    "status": "انتهت",
    "home": "بيتيس",
    "homeLogo": "https://jdwel.com/image/teams/4432.png",
    "away": "جيتكسو",
    "awayLogo": "https://jdwel.com/image/teams/4431.png",
    "score": "1 - 2",
    "time": "6:00 م"
  },
  {
    "date": "السبت 2025/10/04",
    "round": "",
    "status": "انتهت",
    "home": "أتلتيكو كالاتايود",
    "homeLogo": "https://jdwel.com/image/teams/4430.png",
    "away": "أتلتيك سانت جست",
    "awayLogo": "https://jdwel.com/image/teams/4429.png",
    "score": "1 - 4",
    "time": "6:30 م"
  },
  {
    "date": "السبت 2025/10/04",
    "round": "",
    "status": "انتهت",
    "home": "لورديس",
    "homeLogo": "https://jdwel.com/image/teams/4447.png",
    "away": "سانت جوردي",
    "awayLogo": "https://jdwel.com/image/teams/4446.png",
    "score": "1 - 3",
    "time": "6:30 م"
  },
  {
    "date": "السبت 2025/10/04",
    "round": "",
    "status": "انتهت",
    "home": "نيجريرا",
    "homeLogo": "https://jdwel.com/image/teams/4439.png",
    "away": "تكستيل إسكودو",
    "awayLogo": "https://jdwel.com/image/teams/4438.png",
    "score": "4 - 0",
    "time": "6:30 م"
  },
  {
    "date": "السبت 2025/10/04",
    "round": "",
    "status": "انتهت",
    "home": "لوس غاريس",
    "homeLogo": "https://jdwel.com/image/teams/4435.png",
    "away": "مانيسيس",
    "awayLogo": "https://jdwel.com/image/teams/1053.png",
    "score": "4 - 0",
    "time": "7:00 م"
  },
  {
    "date": "السبت 2025/10/04",
    "round": "",
    "status": "انتهت",
    "home": "يونكوس",
    "homeLogo": "https://jdwel.com/image/teams/4440.png",
    "away": "كامباناريو",
    "awayLogo": "https://jdwel.com/image/teams/4441.png",
    "score": "2 - 0",
    "time": "7:00 م"
  },
  {
    "date": "السبت 2025/10/04",
    "round": "",
    "status": "انتهت",
    "home": "بالما ديل ريو",
    "homeLogo": "https://jdwel.com/image/teams/4443.png",
    "away": "أتلتيكو ميليلا",
    "awayLogo": "https://jdwel.com/image/teams/4442.png",
    "score": "2 - 0",
    "time": "7:00 م"
  },
  {
    "date": "السبت 2025/10/04",
    "round": "",
    "status": "انتهت",
    "home": "ماراسينا",
    "homeLogo": "https://jdwel.com/image/teams/4437.png",
    "away": "سبورتينغ دي سيوتا",
    "awayLogo": "https://jdwel.com/image/teams/4436.png",
    "score": "2 - 0",
    "time": "7:30 م"
  },
  {
    "date": "السبت 2025/10/04",
    "round": "",
    "status": "انتهت",
    "home": "أونيفيرسيتاريو",
    "homeLogo": "https://jdwel.com/image/teams/4445.png",
    "away": "إنتر دي فالديمورو",
    "awayLogo": "https://jdwel.com/image/teams/4444.png",
    "score": "1 - 3",
    "time": "9:00 م"
  },
  {
    "date": "الثلاثاء 2025/10/28",
    "round": "",
    "status": "انتهت",
    "home": "كونستانسيا",
    "homeLogo": "https://jdwel.com/image/teams/4758.png",
    "away": "جيرونا",
    "awayLogo": "https://jdwel.com/image/teams/2434.png",
    "score": "2 - 3",
    "time": "9:00 م"
  },
  {
    "date": "الثلاثاء 2025/10/28",
    "round": "",
    "status": "انتهت",
    "home": "أورينسي CF",
    "homeLogo": "https://jdwel.com/image/teams/1159.png",
    "away": "ريال أوفييدو",
    "awayLogo": "https://jdwel.com/image/teams/spa_real_oviedo.png",
    "score": "4 - 2",
    "time": "9:00 م"
  },
  {
    "date": "الثلاثاء 2025/10/28",
    "round": "",
    "status": "انتهت",
    "home": "أتليتيكو تورديسيلاس",
    "homeLogo": "https://jdwel.com/image/teams/4764.png",
    "away": "بورغوس",
    "awayLogo": "https://jdwel.com/image/teams/4767.png",
    "score": "1 - 2",
    "time": "9:00 م"
  },
  {
    "date": "الثلاثاء 2025/10/28",
    "round": "",
    "status": "انتهت",
    "home": "أوكام مورسيا",
    "homeLogo": "https://jdwel.com/image/teams/4769.png",
    "away": "قادش",
    "awayLogo": "https://jdwel.com/image/teams/spa_cadiz.png",
    "score": "1 - 3",
    "time": "9:30 م"
  },
  {
    "date": "الثلاثاء 2025/10/28",
    "round": "",
    "status": "انتهت",
    "home": "لوغرونيس",
    "homeLogo": "https://jdwel.com/image/teams/4763.png",
    "away": "راسينغ سانتاندير",
    "awayLogo": "https://jdwel.com/image/teams/1554.png",
    "score": "0 - 4",
    "time": "9:30 م"
  },
  {
    "date": "الثلاثاء 2025/10/28",
    "round": "",
    "status": "انتهت",
    "home": "لانغريو",
    "homeLogo": "https://jdwel.com/image/teams/1212.png",
    "away": "راسينغ فيرول",
    "awayLogo": "https://jdwel.com/image/teams/1086.png",
    "score": "0 - 03 - 4",
    "time": "9:30 م"
  },
  {
    "date": "الثلاثاء 2025/10/28",
    "round": "",
    "status": "انتهت",
    "home": "ماراسينا",
    "homeLogo": "https://jdwel.com/image/teams/4437.png",
    "away": "فالنسيا",
    "awayLogo": "https://jdwel.com/image/teams/1025.png",
    "score": "0 - 5",
    "time": "10:00 م"
  },
  {
    "date": "الثلاثاء 2025/10/28",
    "round": "",
    "status": "انتهت",
    "home": "إنتر دي فالديمورو",
    "homeLogo": "https://jdwel.com/image/teams/4444.png",
    "away": "خيتافي",
    "awayLogo": "https://jdwel.com/image/teams/1081.png",
    "score": "0 - 11",
    "time": "10:00 م"
  },
  {
    "date": "الثلاثاء 2025/10/28",
    "round": "",
    "status": "انتهت",
    "home": "رودا",
    "homeLogo": "https://jdwel.com/image/teams/4599.png",
    "away": "غرناطة",
    "awayLogo": "https://jdwel.com/image/teams/spa_granada.png",
    "score": "1 - 5",
    "time": "10:00 م"
  },
  {
    "date": "الثلاثاء 2025/10/28",
    "round": "",
    "status": "انتهت",
    "home": "يو دي سان فرناندو",
    "homeLogo": "https://jdwel.com/image/teams/1871.png",
    "away": "ألباسيتي",
    "awayLogo": "https://jdwel.com/image/teams/2160.png",
    "score": "0 - 3",
    "time": "10:00 م"
  },
  {
    "date": "الثلاثاء 2025/10/28",
    "round": "",
    "status": "انتهت",
    "home": "تروبيزون",
    "homeLogo": "https://jdwel.com/image/teams/spa_tropezon.png",
    "away": "كولتورال ليونيسا",
    "awayLogo": "https://jdwel.com/image/teams/3458.png",
    "score": "1 - 3",
    "time": "10:00 م"
  },
  {
    "date": "الثلاثاء 2025/10/28",
    "round": "",
    "status": "انتهت",
    "home": "غوادالاخارا",
    "homeLogo": "https://jdwel.com/image/teams/4771.png",
    "away": "كاسيرينيو",
    "awayLogo": "https://jdwel.com/image/teams/4759.png",
    "score": "2 - 1",
    "time": "10:00 م"
  },
  {
    "date": "الثلاثاء 2025/10/28",
    "round": "",
    "status": "انتهت",
    "home": "رايو ماخاداوندا",
    "homeLogo": "https://jdwel.com/image/teams/4772.png",
    "away": "تالافيرا",
    "awayLogo": "https://jdwel.com/image/teams/4761.png",
    "score": "1 - 4",
    "time": "10:00 م"
  },
  {
    "date": "الثلاثاء 2025/10/28",
    "round": "",
    "status": "انتهت",
    "home": "أوتيبو",
    "homeLogo": "https://jdwel.com/image/teams/1204.png",
    "away": "هويسكا",
    "awayLogo": "https://jdwel.com/image/teams/1027.png",
    "score": "0 - 3",
    "time": "10:30 م"
  },
  {
    "date": "الثلاثاء 2025/10/28",
    "round": "",
    "status": "انتهت",
    "home": "آر إس دي ألكالا",
    "homeLogo": "https://jdwel.com/image/teams/4606.png",
    "away": "تينيريفي",
    "awayLogo": "https://jdwel.com/image/teams/1558.png",
    "score": "0 - 4",
    "time": "10:30 م"
  },
  {
    "date": "الثلاثاء 2025/10/28",
    "round": "",
    "status": "انتهت",
    "home": "توليدو",
    "homeLogo": "https://jdwel.com/image/teams/spa_toledo.png",
    "away": "إشبيلية",
    "awayLogo": "https://jdwel.com/image/teams/1679.png",
    "score": "1 - 4",
    "time": "11:00 م"
  },
  {
    "date": "الثلاثاء 2025/10/28",
    "round": "",
    "status": "انتهت",
    "home": "نيجريرا",
    "homeLogo": "https://jdwel.com/image/teams/4439.png",
    "away": "ريال سوسييداد",
    "awayLogo": "https://jdwel.com/image/teams/2777.png",
    "score": "0 - 3",
    "time": "11:00 م"
  },
  {
    "date": "الثلاثاء 2025/10/28",
    "round": "",
    "status": "انتهت",
    "home": "إكستريمادورا 1924",
    "homeLogo": "https://jdwel.com/image/teams/1201.png",
    "away": "لاس بالماس",
    "awayLogo": "https://jdwel.com/image/teams/1165.png",
    "score": "3 - 1",
    "time": "11:00 م"
  },
  {
    "date": "الأربعاء 2025/10/29",
    "round": "",
    "status": "انتهت",
    "home": "بوبلينسي",
    "homeLogo": "https://jdwel.com/image/teams/4770.png",
    "away": "ساباديل",
    "awayLogo": "https://jdwel.com/image/teams/spa_sabadell.png",
    "score": "1 - 2",
    "time": "8:00 م"
  },
  {
    "date": "الأربعاء 2025/10/29",
    "round": "",
    "status": "انتهت",
    "home": "سانت جوردي",
    "homeLogo": "https://jdwel.com/image/teams/4446.png",
    "away": "أوساسونا",
    "awayLogo": "https://jdwel.com/image/teams/1556.png",
    "score": "0 - 5",
    "time": "9:00 م"
  },
  {
    "date": "الأربعاء 2025/10/29",
    "round": "",
    "status": "انتهت",
    "home": "لوس غاريس",
    "homeLogo": "https://jdwel.com/image/teams/4435.png",
    "away": "إلتشي",
    "awayLogo": "https://jdwel.com/image/teams/2151.png",
    "score": "0 - 4",
    "time": "9:00 م"
  },
  {
    "date": "الأربعاء 2025/10/29",
    "round": "",
    "status": "انتهت",
    "home": "موتيلفيرا",
    "homeLogo": "https://jdwel.com/image/teams/spa_mutilvera.png",
    "away": "ريال سرقسطة",
    "awayLogo": "https://jdwel.com/image/teams/1024.png",
    "score": "1 - 3",
    "time": "9:00 م"
  },
  {
    "date": "الأربعاء 2025/10/29",
    "round": "",
    "status": "انتهت",
    "home": "إيبرو",
    "homeLogo": "https://jdwel.com/image/teams/spa_ebro.png",
    "away": "تارازونا",
    "awayLogo": "https://jdwel.com/image/teams/4773.png",
    "score": "1 - 14 - 3",
    "time": "9:00 م"
  },
  {
    "date": "الأربعاء 2025/10/29",
    "round": "",
    "status": "انتهت",
    "home": "لا يونيون أتلتيكو",
    "homeLogo": "https://jdwel.com/image/teams/822.png",
    "away": "ثيوتا",
    "awayLogo": "https://jdwel.com/image/teams/824.png",
    "score": "0 - 2",
    "time": "9:30 م"
  },
  {
    "date": "الأربعاء 2025/10/29",
    "round": "",
    "status": "انتهت",
    "home": "أتلتيك سانت جست",
    "homeLogo": "https://jdwel.com/image/teams/4429.png",
    "away": "ريال مايوركا",
    "awayLogo": "https://jdwel.com/image/teams/spa_mallorca.png",
    "score": "0 - 2",
    "time": "10:00 م"
  },
  {
    "date": "الأربعاء 2025/10/29",
    "round": "",
    "status": "انتهت",
    "home": "بورتغاليتي",
    "homeLogo": "https://jdwel.com/image/teams/spa_portugalete.png",
    "away": "ريال بلد الوليد",
    "awayLogo": "https://jdwel.com/image/teams/2167.png",
    "score": "1 - 0",
    "time": "10:00 م"
  },
  {
    "date": "الأربعاء 2025/10/29",
    "round": "",
    "status": "انتهت",
    "home": "أزواجا",
    "homeLogo": "https://jdwel.com/image/teams/80.png",
    "away": "ديبورتيفو ليغانيس",
    "awayLogo": "https://jdwel.com/image/teams/1022.png",
    "score": "1 - 4",
    "time": "10:00 م"
  },
  {
    "date": "الأربعاء 2025/10/29",
    "round": "",
    "status": "انتهت",
    "home": "لوركا ديبورتيفا",
    "homeLogo": "https://jdwel.com/image/teams/4774.png",
    "away": "ألميريا",
    "awayLogo": "https://jdwel.com/image/teams/2183.png",
    "score": "0 - 2",
    "time": "10:00 م"
  },
  {
    "date": "الأربعاء 2025/10/29",
    "round": "",
    "status": "انتهت",
    "home": "نكسارا",
    "homeLogo": "https://jdwel.com/image/teams/137.png",
    "away": "إيبار",
    "awayLogo": "https://jdwel.com/image/teams/1026.png",
    "score": "2 - 4",
    "time": "10:00 م"
  },
  {
    "date": "الأربعاء 2025/10/29",
    "round": "",
    "status": "انتهت",
    "home": "كاودال",
    "homeLogo": "https://jdwel.com/image/teams/spa_caudal.png",
    "away": "سبورتينغ خيخون",
    "awayLogo": "https://jdwel.com/image/teams/spa_sporting_gijon.png",
    "score": "0 - 1",
    "time": "10:00 م"
  },
  {
    "date": "الأربعاء 2025/10/29",
    "round": "",
    "status": "انتهت",
    "home": "أتليتيكو آستورغا",
    "homeLogo": "https://jdwel.com/image/teams/spa_atletico_astorga.png",
    "away": "ميرانديس",
    "awayLogo": "https://jdwel.com/image/teams/2159.png",
    "score": "1 - 13 - 4",
    "time": "10:00 م"
  },
  {
    "date": "الأربعاء 2025/10/29",
    "round": "",
    "status": "انتهت",
    "home": "سيزا",
    "homeLogo": "https://jdwel.com/image/teams/4572.png",
    "away": "قرطبة",
    "awayLogo": "https://jdwel.com/image/teams/2158.png",
    "score": "1 - 0",
    "time": "10:00 م"
  },
  {
    "date": "الأربعاء 2025/10/29",
    "round": "",
    "status": "انتهت",
    "home": "سانت اندرو",
    "homeLogo": "https://jdwel.com/image/teams/spa_sant_andreu.png",
    "away": "تيرويل",
    "awayLogo": "https://jdwel.com/image/teams/spa_teruel.png",
    "score": "2 - 1",
    "time": "10:00 م"
  },
  {
    "date": "الأربعاء 2025/10/29",
    "round": "",
    "status": "انتهت",
    "home": "نومانسيا",
    "homeLogo": "https://jdwel.com/image/teams/spa_numancia.png",
    "away": "أريناس كلوب دي غيتسو",
    "awayLogo": "https://jdwel.com/image/teams/spa_arenas_de_getxo.png",
    "score": "3 - 0",
    "time": "10:00 م"
  },
  {
    "date": "الأربعاء 2025/10/29",
    "round": "",
    "status": "انتهت",
    "home": "نابالكارنيرو",
    "homeLogo": "https://jdwel.com/image/teams/833.png",
    "away": "ميريدا",
    "awayLogo": "https://jdwel.com/image/teams/2098.png",
    "score": "2 - 1",
    "time": "10:00 م"
  },
  {
    "date": "الأربعاء 2025/10/29",
    "round": "",
    "status": "انتهت",
    "home": "تورنت",
    "homeLogo": "https://jdwel.com/image/teams/4500.png",
    "away": "جوفنتود توريمولينوس",
    "awayLogo": "https://jdwel.com/image/teams/1205.png",
    "score": "3 - 1",
    "time": "10:00 م"
  },
  {
    "date": "الأربعاء 2025/10/29",
    "round": "",
    "status": "انتهت",
    "home": "بوينتي جينيل",
    "homeLogo": "https://jdwel.com/image/teams/4585.png",
    "away": "كارتاخينا",
    "awayLogo": "https://jdwel.com/image/teams/spa_fc_cartagena.png",
    "score": "0 - 1",
    "time": "10:30 م"
  },
  {
    "date": "الأربعاء 2025/10/29",
    "round": "",
    "status": "انتهت",
    "home": "يو دي أورينسي",
    "homeLogo": "https://jdwel.com/image/teams/4588.png",
    "away": "بونتيفيدرا",
    "awayLogo": "https://jdwel.com/image/teams/spa_pontevedra.png",
    "score": "1 - 10 - 3",
    "time": "10:30 م"
  },
  {
    "date": "الأربعاء 2025/10/29",
    "round": "",
    "status": "انتهت",
    "home": "ريديز",
    "homeLogo": "https://jdwel.com/image/teams/4625.png",
    "away": "يوروبا",
    "awayLogo": "https://jdwel.com/image/teams/838.png",
    "score": "2 - 24 - 3",
    "time": "10:30 م"
  },
  {
    "date": "الأربعاء 2025/10/29",
    "round": "",
    "status": "انتهت",
    "home": "لوسينا",
    "homeLogo": "https://jdwel.com/image/teams/spa_lucena.png",
    "away": "فياريال",
    "awayLogo": "https://jdwel.com/image/teams/1680.png",
    "score": "0 - 6",
    "time": "11:00 م"
  },
  {
    "date": "الأربعاء 2025/10/29",
    "round": "",
    "status": "انتهت",
    "home": "يونكوس",
    "homeLogo": "https://jdwel.com/image/teams/4440.png",
    "away": "رايو فايكانو",
    "awayLogo": "https://jdwel.com/image/teams/1082.png",
    "score": "1 - 6",
    "time": "11:00 م"
  },
  {
    "date": "الأربعاء 2025/10/29",
    "round": "",
    "status": "انتهت",
    "home": "ريال خايين",
    "homeLogo": "https://jdwel.com/image/teams/spa_real_jaen.png",
    "away": "إلدينزي",
    "awayLogo": "https://jdwel.com/image/teams/1085.png",
    "score": "1 - 3",
    "time": "11:00 م"
  },
  {
    "date": "الأربعاء 2025/10/29",
    "round": "",
    "status": "انتهت",
    "home": "كينتانار ديل ري",
    "homeLogo": "https://jdwel.com/image/teams/4701.png",
    "away": "إبيزا",
    "awayLogo": "https://jdwel.com/image/teams/816.png",
    "score": "1 - 14 - 3",
    "time": "11:00 م"
  },
  {
    "date": "الخميس 2025/10/30",
    "round": "",
    "status": "انتهت",
    "home": "بويرتو دي فيغا",
    "homeLogo": "https://jdwel.com/image/teams/4433.png",
    "away": "سيلتا دي فيغو",
    "awayLogo": "https://jdwel.com/image/teams/1163.png",
    "score": "0 - 2",
    "time": "9:00 م"
  },
  {
    "date": "الخميس 2025/10/30",
    "round": "",
    "status": "انتهت",
    "home": "أوريويلا",
    "homeLogo": "https://jdwel.com/image/teams/821.png",
    "away": "ليفانتي",
    "awayLogo": "https://jdwel.com/image/teams/spa_levante.png",
    "score": "3 - 4",
    "time": "9:00 م"
  },
  {
    "date": "الخميس 2025/10/30",
    "round": "",
    "status": "انتهت",
    "home": "فالي إجويس",
    "homeLogo": "https://jdwel.com/image/teams/136.png",
    "away": "أندورا",
    "awayLogo": "https://jdwel.com/image/teams/3457.png",
    "score": "1 - 5",
    "time": "9:30 م"
  },
  {
    "date": "الخميس 2025/10/30",
    "round": "",
    "status": "انتهت",
    "home": "جيتكسو",
    "homeLogo": "https://jdwel.com/image/teams/4431.png",
    "away": "ديبورتيفو ألافيس",
    "awayLogo": "https://jdwel.com/image/teams/4507.png",
    "score": "0 - 7",
    "time": "10:00 م"
  },
  {
    "date": "الخميس 2025/10/30",
    "round": "",
    "status": "انتهت",
    "home": "لوغرونيس",
    "homeLogo": "https://jdwel.com/image/teams/4762.png",
    "away": "بونفيرادينا",
    "awayLogo": "https://jdwel.com/image/teams/spa_ponferradina.png",
    "score": "1 - 3",
    "time": "10:00 م"
  },
  {
    "date": "الخميس 2025/10/30",
    "round": "",
    "status": "انتهت",
    "home": "أتليتيكو بالياريس",
    "homeLogo": "https://jdwel.com/image/teams/4423.png",
    "away": "خيمناستيك طركونة",
    "awayLogo": "https://jdwel.com/image/teams/4794.png",
    "score": "2 - 0",
    "time": "10:00 م"
  },
  {
    "date": "الخميس 2025/10/30",
    "round": "",
    "status": "انتهت",
    "home": "ريال أفيلا",
    "homeLogo": "https://jdwel.com/image/teams/spa_real_avila.png",
    "away": "ريال أفيليس",
    "awayLogo": "https://jdwel.com/image/teams/spa_real_aviles.png",
    "score": "1 - 0",
    "time": "10:00 م"
  },
  {
    "date": "الخميس 2025/10/30",
    "round": "",
    "status": "انتهت",
    "home": "بالما ديل ريو",
    "homeLogo": "https://jdwel.com/image/teams/4443.png",
    "away": "ريال بيتيس",
    "awayLogo": "https://jdwel.com/image/teams/2776.png",
    "score": "1 - 7",
    "time": "11:00 م"
  },
  {
    "date": "الخميس 2025/10/30",
    "round": "",
    "status": "انتهت",
    "home": "أتلتيك ليدا",
    "homeLogo": "https://jdwel.com/image/teams/4569.png",
    "away": "إسبانيول",
    "awayLogo": "https://jdwel.com/image/teams/1164.png",
    "score": "1 - 2",
    "time": "11:00 م"
  },
  {
    "date": "الخميس 2025/10/30",
    "round": "",
    "status": "انتهت",
    "home": "سامانو",
    "homeLogo": "https://jdwel.com/image/teams/4581.png",
    "away": "ديبورتيفو لاكورونيا",
    "awayLogo": "https://jdwel.com/image/teams/2156.png",
    "score": "1 - 5",
    "time": "11:00 م"
  },
  {
    "date": "الخميس 2025/10/30",
    "round": "",
    "status": "انتهت",
    "home": "يونيون إستيبونا",
    "homeLogo": "https://jdwel.com/image/teams/1211.png",
    "away": "مالقا",
    "awayLogo": "https://jdwel.com/image/teams/1084.png",
    "score": "1 - 3",
    "time": "11:00 م"
  },
  {
    "date": "الخميس 2025/10/30",
    "round": "",
    "status": "انتهت",
    "home": "أنتونيانو",
    "homeLogo": "https://jdwel.com/image/teams/4793.png",
    "away": "كاستيلون",
    "awayLogo": "https://jdwel.com/image/teams/2157.png",
    "score": "1 - 0",
    "time": "11:00 م"
  },
  {
    "date": "الخميس 2025/10/30",
    "round": "",
    "status": "انتهت",
    "home": "ريال مورسيا",
    "homeLogo": "https://jdwel.com/image/teams/spa_real_murcia.png",
    "away": "أنتقيرة",
    "awayLogo": "https://jdwel.com/image/teams/3423.png",
    "score": "1 - 12 - 1",
    "time": "11:00 م"
  },
  {
    "date": "الثلاثاء 2025/12/02",
    "round": "",
    "status": "انتهت",
    "home": "نومانسيا",
    "homeLogo": "https://jdwel.com/image/teams/spa_numancia.png",
    "away": "ريال مايوركا",
    "awayLogo": "https://jdwel.com/image/teams/spa_mallorca.png",
    "score": "2 - 3",
    "time": "8:00 م"
  },
  {
    "date": "الثلاثاء 2025/12/02",
    "round": "",
    "status": "انتهت",
    "home": "إيبرو",
    "homeLogo": "https://jdwel.com/image/teams/spa_ebro.png",
    "away": "أوساسونا",
    "awayLogo": "https://jdwel.com/image/teams/1556.png",
    "score": "3 - 5",
    "time": "8:00 م"
  },
  {
    "date": "الثلاثاء 2025/12/02",
    "round": "",
    "status": "انتهت",
    "home": "بورتغاليتي",
    "homeLogo": "https://jdwel.com/image/teams/spa_portugalete.png",
    "away": "ديبورتيفو ألافيس",
    "awayLogo": "https://jdwel.com/image/teams/4507.png",
    "score": "0 - 3",
    "time": "8:00 م"
  },
  {
    "date": "الثلاثاء 2025/12/02",
    "round": "",
    "status": "انتهت",
    "home": "راسينغ فيرول",
    "homeLogo": "https://jdwel.com/image/teams/1086.png",
    "away": "هويسكا",
    "awayLogo": "https://jdwel.com/image/teams/1027.png",
    "score": "0 - 2",
    "time": "8:00 م"
  },
  {
    "date": "الثلاثاء 2025/12/02",
    "round": "",
    "status": "انتهت",
    "home": "غوادالاخارا",
    "homeLogo": "https://jdwel.com/image/teams/4771.png",
    "away": "ثيوتا",
    "awayLogo": "https://jdwel.com/image/teams/824.png",
    "score": "1 - 0",
    "time": "9:00 م"
  },
  {
    "date": "الثلاثاء 2025/12/02",
    "round": "",
    "status": "انتهت",
    "home": "نابالكارنيرو",
    "homeLogo": "https://jdwel.com/image/teams/833.png",
    "away": "خيتافي",
    "awayLogo": "https://jdwel.com/image/teams/1081.png",
    "score": "2 - 3",
    "time": "10:00 م"
  },
  {
    "date": "الأربعاء 2025/12/03",
    "round": "",
    "status": "انتهت",
    "home": "إلدينزي",
    "homeLogo": "https://jdwel.com/image/teams/1085.png",
    "away": "ألميريا",
    "awayLogo": "https://jdwel.com/image/teams/2183.png",
    "score": "2 - 1",
    "time": "9:00 م"
  },
  {
    "date": "الأربعاء 2025/12/03",
    "round": "",
    "status": "انتهت",
    "home": "ريال مورسيا",
    "homeLogo": "https://jdwel.com/image/teams/spa_real_murcia.png",
    "away": "قادش",
    "awayLogo": "https://jdwel.com/image/teams/spa_cadiz.png",
    "score": "3 - 2",
    "time": "9:00 م"
  },
  {
    "date": "الأربعاء 2025/12/03",
    "round": "",
    "status": "انتهت",
    "home": "ميرانديس",
    "homeLogo": "https://jdwel.com/image/teams/2159.png",
    "away": "سبورتينغ خيخون",
    "awayLogo": "https://jdwel.com/image/teams/spa_sporting_gijon.png",
    "score": "0 - 2",
    "time": "9:00 م"
  },
  {
    "date": "الأربعاء 2025/12/03",
    "round": "",
    "status": "انتهت",
    "home": "تالافيرا",
    "homeLogo": "https://jdwel.com/image/teams/4761.png",
    "away": "مالقا",
    "awayLogo": "https://jdwel.com/image/teams/1084.png",
    "score": "2 - 1",
    "time": "9:00 م"
  },
  {
    "date": "الأربعاء 2025/12/03",
    "round": "",
    "status": "انتهت",
    "home": "كولتورال ليونيسا",
    "homeLogo": "https://jdwel.com/image/teams/3458.png",
    "away": "أندورا",
    "awayLogo": "https://jdwel.com/image/teams/3457.png",
    "score": "4 - 2",
    "time": "9:00 م"
  },
  {
    "date": "الأربعاء 2025/12/03",
    "round": "",
    "status": "انتهت",
    "home": "تورنت",
    "homeLogo": "https://jdwel.com/image/teams/4500.png",
    "away": "ريال بيتيس",
    "awayLogo": "https://jdwel.com/image/teams/2776.png",
    "score": "1 - 4",
    "time": "10:00 م"
  },
  {
    "date": "الأربعاء 2025/12/03",
    "round": "",
    "status": "انتهت",
    "home": "ريديز",
    "homeLogo": "https://jdwel.com/image/teams/4625.png",
    "away": "ريال سوسييداد",
    "awayLogo": "https://jdwel.com/image/teams/2777.png",
    "score": "0 - 2",
    "time": "10:00 م"
  },
  {
    "date": "الأربعاء 2025/12/03",
    "round": "",
    "status": "انتهت",
    "home": "أنتونيانو",
    "homeLogo": "https://jdwel.com/image/teams/4793.png",
    "away": "فياريال",
    "awayLogo": "https://jdwel.com/image/teams/1680.png",
    "score": "1 - 13 - 5",
    "time": "10:00 م"
  },
  {
    "date": "الأربعاء 2025/12/03",
    "round": "",
    "status": "انتهت",
    "home": "أورينسي CF",
    "homeLogo": "https://jdwel.com/image/teams/1159.png",
    "away": "جيرونا",
    "awayLogo": "https://jdwel.com/image/teams/2434.png",
    "score": "2 - 1",
    "time": "10:00 م"
  },
  {
    "date": "الأربعاء 2025/12/03",
    "round": "",
    "status": "انتهت",
    "home": "سيزا",
    "homeLogo": "https://jdwel.com/image/teams/4572.png",
    "away": "ليفانتي",
    "awayLogo": "https://jdwel.com/image/teams/spa_levante.png",
    "score": "0 - 1",
    "time": "10:00 م"
  },
  {
    "date": "الأربعاء 2025/12/03",
    "round": "",
    "status": "انتهت",
    "home": "كينتانار ديل ري",
    "homeLogo": "https://jdwel.com/image/teams/4701.png",
    "away": "إلتشي",
    "awayLogo": "https://jdwel.com/image/teams/2151.png",
    "score": "1 - 2",
    "time": "10:00 م"
  },
  {
    "date": "الأربعاء 2025/12/03",
    "round": "",
    "status": "انتهت",
    "home": "بونتيفيدرا",
    "homeLogo": "https://jdwel.com/image/teams/spa_pontevedra.png",
    "away": "إيبار",
    "awayLogo": "https://jdwel.com/image/teams/1026.png",
    "score": "0 - 3",
    "time": "10:00 م"
  },
  {
    "date": "الخميس 2025/12/04",
    "round": "",
    "status": "انتهت",
    "home": "ريال أفيلا",
    "homeLogo": "https://jdwel.com/image/teams/spa_real_avila.png",
    "away": "رايو فايكانو",
    "awayLogo": "https://jdwel.com/image/teams/1082.png",
    "score": "1 - 2",
    "time": "8:00 م"
  },
  {
    "date": "الخميس 2025/12/04",
    "round": "",
    "status": "انتهت",
    "home": "أتليتيكو بالياريس",
    "homeLogo": "https://jdwel.com/image/teams/4423.png",
    "away": "إسبانيول",
    "awayLogo": "https://jdwel.com/image/teams/1164.png",
    "score": "1 - 0",
    "time": "8:00 م"
  },
  {
    "date": "الخميس 2025/12/04",
    "round": "",
    "status": "انتهت",
    "home": "ديبورتيفو ليغانيس",
    "homeLogo": "https://jdwel.com/image/teams/1022.png",
    "away": "ألباسيتي",
    "awayLogo": "https://jdwel.com/image/teams/2160.png",
    "score": "1 - 2",
    "time": "8:00 م"
  },
  {
    "date": "الخميس 2025/12/04",
    "round": "",
    "status": "انتهت",
    "home": "ساباديل",
    "homeLogo": "https://jdwel.com/image/teams/spa_sabadell.png",
    "away": "ديبورتيفو لاكورونيا",
    "awayLogo": "https://jdwel.com/image/teams/2156.png",
    "score": "0 - 2",
    "time": "8:00 م"
  },
  {
    "date": "الخميس 2025/12/04",
    "round": "",
    "status": "انتهت",
    "home": "بونفيرادينا",
    "homeLogo": "https://jdwel.com/image/teams/spa_ponferradina.png",
    "away": "راسينغ سانتاندير",
    "awayLogo": "https://jdwel.com/image/teams/1554.png",
    "score": "1 - 2",
    "time": "9:00 م"
  },
  {
    "date": "الخميس 2025/12/04",
    "round": "",
    "status": "انتهت",
    "home": "إكستريمادورا 1924",
    "homeLogo": "https://jdwel.com/image/teams/1201.png",
    "away": "إشبيلية",
    "awayLogo": "https://jdwel.com/image/teams/1679.png",
    "score": "1 - 2",
    "time": "10:00 م"
  },
  {
    "date": "الخميس 2025/12/04",
    "round": "",
    "status": "انتهت",
    "home": "كارتاخينا",
    "homeLogo": "https://jdwel.com/image/teams/spa_fc_cartagena.png",
    "away": "فالنسيا",
    "awayLogo": "https://jdwel.com/image/teams/1025.png",
    "score": "1 - 2",
    "time": "10:00 م"
  },
  {
    "date": "الخميس 2025/12/04",
    "round": "",
    "status": "انتهت",
    "home": "سانت اندرو",
    "homeLogo": "https://jdwel.com/image/teams/spa_sant_andreu.png",
    "away": "سيلتا دي فيغو",
    "awayLogo": "https://jdwel.com/image/teams/1163.png",
    "score": "1 - 16 - 7",
    "time": "10:00 م"
  },
  {
    "date": "الخميس 2025/12/04",
    "round": "",
    "status": "انتهت",
    "home": "ريال سرقسطة",
    "homeLogo": "https://jdwel.com/image/teams/1024.png",
    "away": "بورغوس",
    "awayLogo": "https://jdwel.com/image/teams/4767.png",
    "score": "0 - 1",
    "time": "10:00 م"
  },
  {
    "date": "الجمعة 2025/12/05",
    "round": "",
    "status": "انتهت",
    "home": "تينيريفي",
    "homeLogo": "https://jdwel.com/image/teams/1558.png",
    "away": "غرناطة",
    "awayLogo": "https://jdwel.com/image/teams/spa_granada.png",
    "score": "0 - 1",
    "time": "11:00 م"
  },
  {
    "date": "الثلاثاء 2025/12/16",
    "round": "",
    "status": "انتهت",
    "home": "ديبورتيفو لاكورونيا",
    "homeLogo": "https://jdwel.com/image/teams/2156.png",
    "away": "ريال مايوركا",
    "awayLogo": "https://jdwel.com/image/teams/spa_mallorca.png",
    "score": "1 - 0",
    "time": "8:00 م"
  },
  {
    "date": "الثلاثاء 2025/12/16",
    "round": "",
    "status": "انتهت",
    "home": "إيبار",
    "homeLogo": "https://jdwel.com/image/teams/1026.png",
    "away": "إلتشي",
    "awayLogo": "https://jdwel.com/image/teams/2151.png",
    "score": "0 - 1",
    "time": "8:00 م"
  },
  {
    "date": "الثلاثاء 2025/12/16",
    "round": "",
    "status": "انتهت",
    "home": "إلدينزي",
    "homeLogo": "https://jdwel.com/image/teams/1085.png",
    "away": "ريال سوسييداد",
    "awayLogo": "https://jdwel.com/image/teams/2777.png",
    "score": "1 - 2",
    "time": "10:00 م"
  },
  {
    "date": "الثلاثاء 2025/12/16",
    "round": "",
    "status": "انتهت",
    "home": "سبورتينغ خيخون",
    "homeLogo": "https://jdwel.com/image/teams/spa_sporting_gijon.png",
    "away": "فالنسيا",
    "awayLogo": "https://jdwel.com/image/teams/1025.png",
    "score": "0 - 2",
    "time": "10:00 م"
  },
  {
    "date": "الثلاثاء 2025/12/16",
    "round": "",
    "status": "انتهت",
    "home": "غوادالاخارا",
    "homeLogo": "https://jdwel.com/image/teams/4771.png",
    "away": "برشلونة",
    "awayLogo": "https://jdwel.com/image/teams/3337.png",
    "score": "0 - 2",
    "time": "10:30 م"
  },
  {
    "date": "الأربعاء 2025/12/17",
    "round": "",
    "status": "انتهت",
    "home": "كولتورال ليونيسا",
    "homeLogo": "https://jdwel.com/image/teams/3458.png",
    "away": "ليفانتي",
    "awayLogo": "https://jdwel.com/image/teams/spa_levante.png",
    "score": "1 - 0",
    "time": "7:00 م"
  },
  {
    "date": "الأربعاء 2025/12/17",
    "round": "",
    "status": "انتهت",
    "home": "ألباسيتي",
    "homeLogo": "https://jdwel.com/image/teams/2160.png",
    "away": "سيلتا دي فيغو",
    "awayLogo": "https://jdwel.com/image/teams/1163.png",
    "score": "2 - 23 - 0",
    "time": "8:00 م"
  },
  {
    "date": "الأربعاء 2025/12/17",
    "round": "",
    "status": "انتهت",
    "home": "أتليتيكو بالياريس",
    "homeLogo": "https://jdwel.com/image/teams/4423.png",
    "away": "أتلتيكو مدريد",
    "awayLogo": "https://jdwel.com/image/teams/716.png",
    "score": "2 - 3",
    "time": "8:00 م"
  },
  {
    "date": "الأربعاء 2025/12/17",
    "round": "",
    "status": "انتهت",
    "home": "هويسكا",
    "homeLogo": "https://jdwel.com/image/teams/1027.png",
    "away": "أوساسونا",
    "awayLogo": "https://jdwel.com/image/teams/1556.png",
    "score": "2 - 4",
    "time": "8:00 م"
  },
  {
    "date": "الأربعاء 2025/12/17",
    "round": "",
    "status": "انتهت",
    "home": "راسينغ سانتاندير",
    "homeLogo": "https://jdwel.com/image/teams/1554.png",
    "away": "فياريال",
    "awayLogo": "https://jdwel.com/image/teams/1680.png",
    "score": "2 - 1",
    "time": "8:00 م"
  },
  {
    "date": "الأربعاء 2025/12/17",
    "round": "",
    "status": "انتهت",
    "home": "ديبورتيفو ألافيس",
    "homeLogo": "https://jdwel.com/image/teams/4507.png",
    "away": "إشبيلية",
    "awayLogo": "https://jdwel.com/image/teams/1679.png",
    "score": "1 - 0",
    "time": "10:00 م"
  },
  {
    "date": "الأربعاء 2025/12/17",
    "round": "",
    "status": "انتهت",
    "home": "تالافيرا",
    "homeLogo": "https://jdwel.com/image/teams/4761.png",
    "away": "ريال مدريد",
    "awayLogo": "https://jdwel.com/image/teams/2605.png",
    "score": "2 - 3",
    "time": "10:00 م"
  },
  {
    "date": "الخميس 2025/12/18",
    "round": "",
    "status": "انتهت",
    "home": "بورغوس",
    "homeLogo": "https://jdwel.com/image/teams/4767.png",
    "away": "خيتافي",
    "awayLogo": "https://jdwel.com/image/teams/1081.png",
    "score": "3 - 1",
    "time": "8:00 م"
  },
  {
    "date": "الخميس 2025/12/18",
    "round": "",
    "status": "انتهت",
    "home": "أورينسي CF",
    "homeLogo": "https://jdwel.com/image/teams/1159.png",
    "away": "أتلتيك بيلباو",
    "awayLogo": "https://jdwel.com/image/teams/2033.png",
    "score": "0 - 1",
    "time": "8:00 م"
  },
  {
    "date": "الخميس 2025/12/18",
    "round": "",
    "status": "انتهت",
    "home": "ريال مورسيا",
    "homeLogo": "https://jdwel.com/image/teams/spa_real_murcia.png",
    "away": "ريال بيتيس",
    "awayLogo": "https://jdwel.com/image/teams/2776.png",
    "score": "0 - 2",
    "time": "10:00 م"
  },
  {
    "date": "الثلاثاء 2026/01/06",
    "round": "",
    "status": "انتهت",
    "home": "غرناطة",
    "homeLogo": "https://jdwel.com/image/teams/spa_granada.png",
    "away": "رايو فايكانو",
    "awayLogo": "https://jdwel.com/image/teams/1082.png",
    "score": "1 - 3",
    "time": "8:00 م"
  },
  {
    "date": "الثلاثاء 2026/01/13",
    "round": "",
    "status": "انتهت",
    "home": "ريال سوسييداد",
    "homeLogo": "https://jdwel.com/image/teams/2777.png",
    "away": "أوساسونا",
    "awayLogo": "https://jdwel.com/image/teams/1556.png",
    "score": "2 - 24 - 3",
    "time": "10:00 م"
  },
  {
    "date": "الثلاثاء 2026/01/13",
    "round": "",
    "status": "انتهت",
    "home": "كولتورال ليونيسا",
    "homeLogo": "https://jdwel.com/image/teams/3458.png",
    "away": "أتلتيك بيلباو",
    "awayLogo": "https://jdwel.com/image/teams/2033.png",
    "score": "3 - 4",
    "time": "10:00 م"
  },
  {
    "date": "الثلاثاء 2026/01/13",
    "round": "",
    "status": "انتهت",
    "home": "ديبورتيفو لاكورونيا",
    "homeLogo": "https://jdwel.com/image/teams/2156.png",
    "away": "أتلتيكو مدريد",
    "awayLogo": "https://jdwel.com/image/teams/716.png",
    "score": "0 - 1",
    "time": "10:00 م"
  },
  {
    "date": "الأربعاء 2026/01/14",
    "round": "",
    "status": "انتهت",
    "home": "ألباسيتي",
    "homeLogo": "https://jdwel.com/image/teams/2160.png",
    "away": "ريال مدريد",
    "awayLogo": "https://jdwel.com/image/teams/2605.png",
    "score": "3 - 2",
    "time": "10:00 م"
  },
  {
    "date": "الأربعاء 2026/01/14",
    "round": "",
    "status": "انتهت",
    "home": "ديبورتيفو ألافيس",
    "homeLogo": "https://jdwel.com/image/teams/4507.png",
    "away": "رايو فايكانو",
    "awayLogo": "https://jdwel.com/image/teams/1082.png",
    "score": "2 - 0",
    "time": "10:00 م"
  },
  {
    "date": "الأربعاء 2026/01/14",
    "round": "",
    "status": "انتهت",
    "home": "ريال بيتيس",
    "homeLogo": "https://jdwel.com/image/teams/2776.png",
    "away": "إلتشي",
    "awayLogo": "https://jdwel.com/image/teams/2151.png",
    "score": "2 - 1",
    "time": "10:00 م"
  },
  {
    "date": "الخميس 2026/01/15",
    "round": "",
    "status": "انتهت",
    "home": "بورغوس",
    "homeLogo": "https://jdwel.com/image/teams/4767.png",
    "away": "فالنسيا",
    "awayLogo": "https://jdwel.com/image/teams/1025.png",
    "score": "0 - 2",
    "time": "10:00 م"
  },
  {
    "date": "الخميس 2026/01/15",
    "round": "",
    "status": "انتهت",
    "home": "راسينغ سانتاندير",
    "homeLogo": "https://jdwel.com/image/teams/1554.png",
    "away": "برشلونة",
    "awayLogo": "https://jdwel.com/image/teams/3337.png",
    "score": "0 - 2",
    "time": "10:15 م"
  },
  {
    "date": "الثلاثاء 2026/02/03",
    "round": "",
    "status": "قريباً",
    "home": "ألباسيتي",
    "homeLogo": "https://jdwel.com/image/teams/2160.png",
    "away": "برشلونة",
    "awayLogo": "https://jdwel.com/image/teams/3337.png",
    "score": "0 - 0",
    "time": "10:00 م"
  },
  {
    "date": "الأربعاء 2026/02/04",
    "round": "",
    "status": "قريباً",
    "home": "ديبورتيفو ألافيس",
    "homeLogo": "https://jdwel.com/image/teams/4507.png",
    "away": "ريال سوسييداد",
    "awayLogo": "https://jdwel.com/image/teams/2777.png",
    "score": "0 - 0",
    "time": "10:00 م"
  },
  {
    "date": "الأربعاء 2026/02/04",
    "round": "",
    "status": "قريباً",
    "home": "فالنسيا",
    "homeLogo": "https://jdwel.com/image/teams/1025.png",
    "away": "أتلتيك بيلباو",
    "awayLogo": "https://jdwel.com/image/teams/2033.png",
    "score": "0 - 0",
    "time": "10:00 م"
  },
  {
    "date": "الخميس 2026/02/05",
    "round": "",
    "status": "قريباً",
    "home": "ريال بيتيس",
    "homeLogo": "https://jdwel.com/image/teams/2776.png",
    "away": "أتلتيكو مدريد",
    "awayLogo": "https://jdwel.com/image/teams/716.png",
    "score": "0 - 0",
    "time": "10:00 م"
  }
]